[
  {
    "owner": "BJjpgZYnrdXpMoAE1chy16UNJoG1CLgTYag6pcTtj7dh",
    "amount": 47572.096448747,
    "percentage": 0.07044096116060686,
    "double_amount_for_100_apy": 95144.192897494,
    "sol_equivalent_for_100_apy": 0.12921542424169766,
    "daily_sol_for_100_apy": 0.00035401486093615797
  },
  {
    "owner": "5gpRqRf375S1Rsz575cAbfnM9cT5dkC2EB5kjSodHxwL",
    "amount": 597972.327999999,
    "percentage": 0.8854296673081568,
    "double_amount_for_100_apy": 1195944.655999998,
    "sol_equivalent_for_100_apy": 1.624213642351484,
    "daily_sol_for_100_apy": 0.004449900390004065
  },
  {
    "owner": "3pwLmqsNcNMk7zhXNnkLwDNqdvgdRhQntZcn55C3gy9B",
    "amount": 70164.014660916,
    "percentage": 0.10389326938590306,
    "double_amount_for_100_apy": 140328.029321832,
    "sol_equivalent_for_100_apy": 0.19057963801697775,
    "daily_sol_for_100_apy": 0.0005221359945670623
  },
  {
    "owner": "H9818nzG9mSndrCX5SR4ZRzEK9x1NjFmeYDbDVUijW1x",
    "amount": 761474.302820522,
    "percentage": 1.1275303338285687,
    "double_amount_for_100_apy": 1522948.605641044,
    "sol_equivalent_for_100_apy": 2.0683180358492756,
    "daily_sol_for_100_apy": 0.00566662475575144
  },
  {
    "owner": "HdTyU6wjJAxP3Xqq5EbSobHbREvuGbVu5NL55dGcY4qY",
    "amount": 49858.750160154,
    "percentage": 0.07382685535693506,
    "double_amount_for_100_apy": 99717.500320308,
    "sol_equivalent_for_100_apy": 0.1354264376607014,
    "daily_sol_for_100_apy": 0.00037103133605671617
  },
  {
    "owner": "9Q4SR95AR7arXXAMT4HG6kkmuwZjSXJZovhL2Yf4QCn6",
    "amount": 161916.082138096,
    "percentage": 0.2397524032907669,
    "double_amount_for_100_apy": 323832.164276192,
    "sol_equivalent_for_100_apy": 0.43979678859788207,
    "daily_sol_for_100_apy": 0.0012049227084873482
  },
  {
    "owner": "FTchTFMP5w6y1ZL2PksHHNjPpprrsDq67MAEpNrKFYSc",
    "amount": 79308.907714371,
    "percentage": 0.11743429667887395,
    "double_amount_for_100_apy": 158617.815428742,
    "sol_equivalent_for_100_apy": 0.21541901495762264,
    "daily_sol_for_100_apy": 0.0005901890820756785
  },
  {
    "owner": "FYAaKu2MTKpvXgkmVKB1Cjkt7Wm7MfxuzEzohxhgfRx3",
    "amount": 86327.785842965,
    "percentage": 0.12782729086150357,
    "double_amount_for_100_apy": 172655.57168593,
    "sol_equivalent_for_100_apy": 0.2344837058750004,
    "daily_sol_for_100_apy": 0.0006424211119863024
  },
  {
    "owner": "ATvAMJwdvzSidrxdrcjYaQkGEFu2tLcaWjkFx6Wqf47f",
    "amount": 87206.572333993,
    "percentage": 0.12912852771470093,
    "double_amount_for_100_apy": 174413.144667986,
    "sol_equivalent_for_100_apy": 0.23687066751286717,
    "daily_sol_for_100_apy": 0.0006489607329119648
  },
  {
    "owner": "6wiDe9s5NbeVJSe4AjqWhrUFPVNAu7XyamLQAEok3Ejt",
    "amount": 1262650.250232297,
    "percentage": 1.869631651232104,
    "double_amount_for_100_apy": 2525300.500464594,
    "sol_equivalent_for_100_apy": 3.4296131541823036,
    "daily_sol_for_100_apy": 0.00939620042241727
  },
  {
    "owner": "2cy8vkc7Es7yMNu5n7gnr2PM8ikfCRwweWPbUGyjzw66",
    "amount": 84743.396694646,
    "percentage": 0.12548125394508836,
    "double_amount_for_100_apy": 169486.793389292,
    "sol_equivalent_for_100_apy": 0.2301801848774646,
    "daily_sol_for_100_apy": 0.0006306306434999031
  },
  {
    "owner": "8otm8ek2xjXDodyE3c2nXzVdhHQFm2srQF6D7nvnjNLH",
    "amount": 112022.574383411,
    "percentage": 0.16587408166370365,
    "double_amount_for_100_apy": 224045.148766822,
    "sol_equivalent_for_100_apy": 0.3042759422888718,
    "daily_sol_for_100_apy": 0.0008336327185996487
  },
  {
    "owner": "5NMb27gbokooTpno5itgqBa4pSU2bQxZk4kqQarrBfds",
    "amount": 62487.013692412,
    "percentage": 0.09252577946174238,
    "double_amount_for_100_apy": 124974.027384824,
    "sol_equivalent_for_100_apy": 0.16972735251558282,
    "daily_sol_for_100_apy": 0.0004650064452481721
  },
  {
    "owner": "3EwJnK4vR8LkwEz7T53cACNSnkJmchG7nM9JVeYwEA4L",
    "amount": 86029.128782288,
    "percentage": 0.12738506333776692,
    "double_amount_for_100_apy": 172058.257564576,
    "sol_equivalent_for_100_apy": 0.2336724929649338,
    "daily_sol_for_100_apy": 0.0006401986108628323
  },
  {
    "owner": "DiZ7ojw72wLzoue5ZLAATiPVjwS5QRSSkLaa4LJFVqJU",
    "amount": 29716.10637956,
    "percentage": 0.044001237102977854,
    "double_amount_for_100_apy": 59432.21275912,
    "sol_equivalent_for_100_apy": 0.08071494803225977,
    "daily_sol_for_100_apy": 0.00022113684392399937
  },
  {
    "owner": "D2MQVUmGPum9Joc53A9FNDFXBSGCCP38bpGXFUh5e62n",
    "amount": 106793.85609458,
    "percentage": 0.15813181320387,
    "double_amount_for_100_apy": 213587.71218916,
    "sol_equivalent_for_100_apy": 0.2900736871358005,
    "daily_sol_for_100_apy": 0.0007947224305090425
  },
  {
    "owner": "G8WCFY8HUGywg6PcW8ayfJh1xG9sB1YBuhRcGK8yRJEk",
    "amount": 47839.07432962,
    "percentage": 0.07083628068489096,
    "double_amount_for_100_apy": 95678.14865924,
    "sol_equivalent_for_100_apy": 0.12994059009974054,
    "daily_sol_for_100_apy": 0.0003560016167116179
  },
  {
    "owner": "7Ekwo8CXReGdMTVxLYVFtNyVrtcwvu13nfdvu3GgYjHu",
    "amount": 85935.132228688,
    "percentage": 0.12724588074806328,
    "double_amount_for_100_apy": 171870.264457376,
    "sol_equivalent_for_100_apy": 0.233417179336623,
    "daily_sol_for_100_apy": 0.0006394991214702001
  },
  {
    "owner": "ABFh3exo6T5PAa84egnFuh9sb3ZEukb64gF9BTr4fYQN",
    "amount": 78965.073993539,
    "percentage": 0.11692517516473325,
    "double_amount_for_100_apy": 157930.147987078,
    "sol_equivalent_for_100_apy": 0.21448509311220273,
    "daily_sol_for_100_apy": 0.0005876303920882267
  },
  {
    "owner": "8g6WUHP8DN6ZKi7DCb4VKZmn5VhTaDKDgkaPorSafMy2",
    "amount": 24429.231082716,
    "percentage": 0.03617285439028433,
    "double_amount_for_100_apy": 48858.462165432,
    "sol_equivalent_for_100_apy": 0.06635472669682518,
    "daily_sol_for_100_apy": 0.0001817937717721238
  },
  {
    "owner": "DJoiju2i7qqJTi8fuUPYyycjE5zE99mPZwsHeKZ8z2fm",
    "amount": 43828.528403956,
    "percentage": 0.06489778457327028,
    "double_amount_for_100_apy": 87657.056807912,
    "sol_equivalent_for_100_apy": 0.11904713717437265,
    "daily_sol_for_100_apy": 0.0003261565402037607
  },
  {
    "owner": "2s2As1LnQ8PUtcTviaEXRfa5DQT9oYmAzy3CR6B9aVhu",
    "amount": 1195664.328999999,
    "percentage": 1.770444248782531,
    "double_amount_for_100_apy": 2391328.657999998,
    "sol_equivalent_for_100_apy": 3.2476658599406534,
    "daily_sol_for_100_apy": 0.008897714684768913
  },
  {
    "owner": "DXhK4NoqyG2NCh135JFQKaecq7wKebiJzRnCsES7jjth",
    "amount": 84085.013457538,
    "percentage": 0.12450637262818268,
    "double_amount_for_100_apy": 168170.026915076,
    "sol_equivalent_for_100_apy": 0.22839188300205351,
    "daily_sol_for_100_apy": 0.0006257311863069959
  },
  {
    "owner": "88Y4YTghWPhm5B9aCJh5F3njQsL9vgHMMkyeZsoR2aWv",
    "amount": 102497.777542113,
    "percentage": 0.1517705231820338,
    "double_amount_for_100_apy": 204995.555084226,
    "sol_equivalent_for_100_apy": 0.27840466991410306,
    "daily_sol_for_100_apy": 0.0007627525203126111
  },
  {
    "owner": "CXdzKKn2ZSaaapjgzUJpJsKcDD1ARVPbx52e8evSo4fp",
    "amount": 44467.505251099,
    "percentage": 0.06584393045777255,
    "double_amount_for_100_apy": 88935.010502198,
    "sol_equivalent_for_100_apy": 0.12078272737425294,
    "daily_sol_for_100_apy": 0.0003309115818472683
  },
  {
    "owner": "57CJEn2p9VR9DGZGvyz5wvxQBdLJbhaSrDVjPKoDQCZ9",
    "amount": 70335.968972195,
    "percentage": 0.1041478855972204,
    "double_amount_for_100_apy": 140671.93794439,
    "sol_equivalent_for_100_apy": 0.19104670066379725,
    "daily_sol_for_100_apy": 0.0005234156182569788
  },
  {
    "owner": "8RknfWhm9Cw4WDeL9Z8oh3uvRYj3ZEvb6hFESFKa3PB1",
    "amount": 84276.2115181,
    "percentage": 0.12478948344657051,
    "double_amount_for_100_apy": 168552.4230362,
    "sol_equivalent_for_100_apy": 0.22891121555945562,
    "daily_sol_for_100_apy": 0.0006271540152313853
  },
  {
    "owner": "6ZnHXdEGCP5VUuRaPqnWjVYCrvAKvr1UL6biaNdLo2mp",
    "amount": 387002.82151716,
    "percentage": 0.5730428708120042,
    "double_amount_for_100_apy": 774005.64303432,
    "sol_equivalent_for_100_apy": 1.0511778436956178,
    "daily_sol_for_100_apy": 0.0028799392977962132
  },
  {
    "owner": "5twSDrFqGfQ3RMEX1kXVweafMDiqQDhdDkhCyCrwXucp",
    "amount": 84923.745339084,
    "percentage": 0.12574829981454907,
    "double_amount_for_100_apy": 169847.490678168,
    "sol_equivalent_for_100_apy": 0.2306700482289269,
    "daily_sol_for_100_apy": 0.0006319727348737724
  },
  {
    "owner": "MXTEi69QBHmupFUjGNNyW5sc336ErrksbRHrhG4ypo1",
    "amount": 102869.248085874,
    "percentage": 0.15232056709640215,
    "double_amount_for_100_apy": 205738.496171748,
    "sol_equivalent_for_100_apy": 0.2794136589536566,
    "daily_sol_for_100_apy": 0.0007655168738456346
  },
  {
    "owner": "FTbZTMKAjmGQhmYoHuEyr7eNPS3pveX7pjdiiH4ayMeM",
    "amount": 2210153.827156928,
    "percentage": 3.272619277257611,
    "double_amount_for_100_apy": 4420307.654313856,
    "sol_equivalent_for_100_apy": 6.003224279240613,
    "daily_sol_for_100_apy": 0.016447189806138667
  },
  {
    "owner": "GME8jEUdr1xu2hBBU4pJLQRQHRBYW2kHwnH2YVGLHatF",
    "amount": 849952.157830775,
    "percentage": 1.2585412754015504,
    "double_amount_for_100_apy": 1699904.31566155,
    "sol_equivalent_for_100_apy": 2.3086417639292978,
    "daily_sol_for_100_apy": 0.006325045928573418
  },
  {
    "owner": "HtEWNdyGkZxqQvND4vcEceSzJTjBkvjqsy2HBxx2sCC5",
    "amount": 89325.621112017,
    "percentage": 0.1322662459111449,
    "double_amount_for_100_apy": 178651.242224034,
    "sol_equivalent_for_100_apy": 0.24262643207405743,
    "daily_sol_for_100_apy": 0.0006647299508878286
  },
  {
    "owner": "FRVRPe9P1kt8Ey1rPkP5vuvddL3NeytALjrifrXmwe4L",
    "amount": 1396758.918038897,
    "percentage": 2.068209056170377,
    "double_amount_for_100_apy": 2793517.836077794,
    "sol_equivalent_for_100_apy": 3.7938793879352866,
    "daily_sol_for_100_apy": 0.010394190103932293
  },
  {
    "owner": "9J7zDLKnaRWK9LtZuyGzikJAVzABj1kcn5eMNp5Xmiah",
    "amount": 222837.217422955,
    "percentage": 0.32995955506269303,
    "double_amount_for_100_apy": 445674.43484591,
    "sol_equivalent_for_100_apy": 0.6052708990273006,
    "daily_sol_for_100_apy": 0.0016582764356912344
  },
  {
    "owner": "FAMmEYXoJNnK47n51ZvW1s5CTsWdFTDmCZZY2TdBBLgD",
    "amount": 475475.614463104,
    "percentage": 0.7040463168844299,
    "double_amount_for_100_apy": 950951.228926208,
    "sol_equivalent_for_100_apy": 1.2914878221863626,
    "daily_sol_for_100_apy": 0.0035383228005105823
  },
  {
    "owner": "82sxBeYejDgAeLFATgTkR9cRMS5Hdm3jFVGZ5MbCnAXB",
    "amount": 89616.279366247,
    "percentage": 0.13269662944110525,
    "double_amount_for_100_apy": 179232.558732494,
    "sol_equivalent_for_100_apy": 0.24341591860993345,
    "daily_sol_for_100_apy": 0.0006668929276984478
  },
  {
    "owner": "3sE5HnfrktWSWdyQLLVjVVdoUsMk9QU1yN3FPS8PENzG",
    "amount": 85375.098557862,
    "percentage": 0.12641662761439515,
    "double_amount_for_100_apy": 170750.197115724,
    "sol_equivalent_for_100_apy": 0.23189601475134178,
    "daily_sol_for_100_apy": 0.00063533154726395
  },
  {
    "owner": "6ncLPo29tzHkzDwsMZcqa1qH4yWvGTWZfC7Uv7iiNMov",
    "amount": 86233.606923137,
    "percentage": 0.12768783823845387,
    "double_amount_for_100_apy": 172467.213846274,
    "sol_equivalent_for_100_apy": 0.23422789690317364,
    "daily_sol_for_100_apy": 0.0006417202654881469
  },
  {
    "owner": "ECNQ82uFZ6ZjeMG45SpdSMUUX73ZkLZqg8GL1pv9gwxH",
    "amount": 50371.852872961,
    "percentage": 0.07458661687602598,
    "double_amount_for_100_apy": 100743.705745922,
    "sol_equivalent_for_100_apy": 0.13682012828323584,
    "daily_sol_for_100_apy": 0.0003748496665294133
  },
  {
    "owner": "2BZe9ksdrKAdcqZb3vPbD2iuAuasnv84McbGPPrXrwyL",
    "amount": 2042699.69040589,
    "percentage": 3.024666564982861,
    "double_amount_for_100_apy": 4085399.38081178,
    "sol_equivalent_for_100_apy": 5.548385015542734,
    "daily_sol_for_100_apy": 0.01520105483710338
  },
  {
    "owner": "EHeVLBy8YqwgEjYcsE8ARvKjuwVqqVWVbgNLhpH3fyeB",
    "amount": 67072.891425784,
    "percentage": 0.09931618096636761,
    "double_amount_for_100_apy": 134145.782851568,
    "sol_equivalent_for_100_apy": 0.1821835228564597,
    "daily_sol_for_100_apy": 0.0004991329393327663
  },
  {
    "owner": "9y9HNKiqfRaUU3WHAooWfCvA15U7f8acS7LNZvcE8fvr",
    "amount": 81325.203756665,
    "percentage": 0.12041986683041302,
    "double_amount_for_100_apy": 162650.40751333,
    "sol_equivalent_for_100_apy": 0.22089568233095505,
    "daily_sol_for_100_apy": 0.0006051936502217947
  },
  {
    "owner": "9gTVfK8CZjdP3KfNLaWFMgGA1FkDdeviLXNtcAqBxDnP",
    "amount": 84911.209638687,
    "percentage": 0.12572973795054257,
    "double_amount_for_100_apy": 169822.419277374,
    "sol_equivalent_for_100_apy": 0.23063599873424653,
    "daily_sol_for_100_apy": 0.0006318794485869768
  },
  {
    "owner": "4mtzamBuW9nQ7NBk15QhaKXUpvS2tVZXA4kzU4kwvmYg",
    "amount": 1015770.714528828,
    "percentage": 1.504072151356526,
    "double_amount_for_100_apy": 2031541.429057656,
    "sol_equivalent_for_100_apy": 2.7590384617912282,
    "daily_sol_for_100_apy": 0.007559009484359529
  },
  {
    "owner": "DAEWtrSrUieacgRDt46ZmWCs7kYtiGP7s4dYqCGyb8Gq",
    "amount": 86575.936368788,
    "percentage": 0.1281947323420428,
    "double_amount_for_100_apy": 173151.872737576,
    "sol_equivalent_for_100_apy": 0.23515773283331545,
    "daily_sol_for_100_apy": 0.0006442677611871656
  },
  {
    "owner": "J6Pay6vWQKcLNkHKfKnyHLvADz7hbMXMiK3Z6aazmr6t",
    "amount": 85736.458600293,
    "percentage": 0.1269517007058512,
    "double_amount_for_100_apy": 171472.917200586,
    "sol_equivalent_for_100_apy": 0.23287754162680807,
    "daily_sol_for_100_apy": 0.000638020661991255
  },
  {
    "owner": "FFxVkf2W9gWmbourzpZwC3zDizjjPPg8mhRQpWq1gcL2",
    "amount": 528232.304745976,
    "percentage": 0.7821642105362627,
    "double_amount_for_100_apy": 1056464.609491952,
    "sol_equivalent_for_100_apy": 1.4347856506483392,
    "daily_sol_for_100_apy": 0.003930919590817368
  },
  {
    "owner": "H5iSDfqA1hj3GykihjWkLHMZdzCmCJrhLDW2cvV6d1JV",
    "amount": 44749.356564073,
    "percentage": 0.06626127337247167,
    "double_amount_for_100_apy": 89498.713128146,
    "sol_equivalent_for_100_apy": 0.12154829247854161,
    "daily_sol_for_100_apy": 0.0003330090204891551
  },
  {
    "owner": "9r89sTj1CkHjzKL3A1M5cRKsLdMd4z2YRT5bkXPu65g7",
    "amount": 1188427.789508687,
    "percentage": 1.7597289590371255,
    "double_amount_for_100_apy": 2376855.579017374,
    "sol_equivalent_for_100_apy": 3.2280099567912286,
    "daily_sol_for_100_apy": 0.008843862895318435
  },
  {
    "owner": "EY9ksz8A7wPaHLipbdvyRNoBUGeMUbiEKoXdVd3GL6iX",
    "amount": 593807.212317861,
    "percentage": 0.8792622966455874,
    "double_amount_for_100_apy": 1187614.424635722,
    "sol_equivalent_for_100_apy": 1.6129003467420913,
    "daily_sol_for_100_apy": 0.0044189050595673735
  },
  {
    "owner": "S1n39sNU9YSwwviMVjgYk5ZLdyqoojDnFPvbxGxixqB",
    "amount": 87135.542166287,
    "percentage": 0.12902335191505968,
    "double_amount_for_100_apy": 174271.084332574,
    "sol_equivalent_for_100_apy": 0.23667773522820368,
    "daily_sol_for_100_apy": 0.000648432151310147
  },
  {
    "owner": "UkFYxgVPxz4YNELAHaGh3aeRWKmEqegTevaCDdfqdJu",
    "amount": 85374.639190753,
    "percentage": 0.12641594742026668,
    "double_amount_for_100_apy": 170749.278381506,
    "sol_equivalent_for_100_apy": 0.2318947670174746,
    "daily_sol_for_100_apy": 0.0006353281288149989
  },
  {
    "owner": "3AM6w3nzniZNt196FsDh7JKLXsEmAzCi8oL9agJaR9f4",
    "amount": 85848.183672831,
    "percentage": 0.1271171342705417,
    "double_amount_for_100_apy": 171696.367345662,
    "sol_equivalent_for_100_apy": 0.2331810094939849,
    "daily_sol_for_100_apy": 0.000638852080805438
  },
  {
    "owner": "2S1kLZqWPFpa9bmJ5K9CFb8fHjRQ9t4XCskMp9AZodNi",
    "amount": 43075.100663788,
    "percentage": 0.06378216894679317,
    "double_amount_for_100_apy": 86150.201327576,
    "sol_equivalent_for_100_apy": 0.11700067522821565,
    "daily_sol_for_100_apy": 0.0003205497951457963
  },
  {
    "owner": "E9mNQqUicjt876kNYUivojW4pSwyDvsuQNXGxV79kqm3",
    "amount": 2015067,
    "percentage": 2.98375028386539,
    "double_amount_for_100_apy": 4030134,
    "sol_equivalent_for_100_apy": 5.47332904617667,
    "daily_sol_for_100_apy": 0.014995422044319645
  },
  {
    "owner": "DKiqtUZBQrKWep7vVifxcS38BE9r3V7Uh7ogvXZznp3Z",
    "amount": 377602.690595826,
    "percentage": 0.5591239076683956,
    "double_amount_for_100_apy": 755205.381191652,
    "sol_equivalent_for_100_apy": 1.025645189143883,
    "daily_sol_for_100_apy": 0.002809986819572282
  },
  {
    "owner": "AeLdhWxM8zmLnK6eKMZkQhCFEr5HxoyQbvjuQ92xa2LE",
    "amount": 441126.796122777,
    "percentage": 0.6531853298932322,
    "double_amount_for_100_apy": 882253.592245554,
    "sol_equivalent_for_100_apy": 1.1981894925903949,
    "daily_sol_for_100_apy": 0.0032827109386038217
  },
  {
    "owner": "AtKYpjYmNPwC2uBsPEHbVNUXoE2nftfUSTRiwWcjcdb5",
    "amount": 335112.862042196,
    "percentage": 0.4962083629206104,
    "double_amount_for_100_apy": 670225.724084392,
    "sol_equivalent_for_100_apy": 0.9102342312007227,
    "daily_sol_for_100_apy": 0.002493792414248555
  },
  {
    "owner": "CvxkiiPuVUsRPMWQou2qBzB6Ssxjpiix14yFj5FMKxrW",
    "amount": 83722.494870459,
    "percentage": 0.12396958405633694,
    "double_amount_for_100_apy": 167444.989740918,
    "sol_equivalent_for_100_apy": 0.22740720928527963,
    "daily_sol_for_100_apy": 0.0006230334500966565
  },
  {
    "owner": "HdbfQg4wsYaM6J7jeP84CCvzqrsjgXJHoMerbhjdJxwt",
    "amount": 84120.787063044,
    "percentage": 0.1245593433262207,
    "double_amount_for_100_apy": 168241.574126088,
    "sol_equivalent_for_100_apy": 0.2284890513414201,
    "daily_sol_for_100_apy": 0.0006259974009353976
  },
  {
    "owner": "GK2RYjoxaEWU6Fw9wj4p9MZ8nE34xLPWowvpBY2LpzwG",
    "amount": 289855.127735506,
    "percentage": 0.42919432438755384,
    "double_amount_for_100_apy": 579710.255471012,
    "sol_equivalent_for_100_apy": 0.7873050820731985,
    "daily_sol_for_100_apy": 0.002157000224858078
  },
  {
    "owner": "2hiwSGtEfvwzHfgXE3XpzGPNCN2iwsfJoHunoCkcNwhj",
    "amount": 123224.745504408,
    "percentage": 0.18246136201824445,
    "double_amount_for_100_apy": 246449.491008816,
    "sol_equivalent_for_100_apy": 0.334703302062415,
    "daily_sol_for_100_apy": 0.0009169953481162054
  },
  {
    "owner": "8wHNDU4WaLttQ3M6SgEXZGW9qFEMi9aoSTGtPvwJbMYa",
    "amount": 40528.654272846,
    "percentage": 0.060011594498488884,
    "double_amount_for_100_apy": 81057.308545692,
    "sol_equivalent_for_100_apy": 0.11008401240952297,
    "daily_sol_for_100_apy": 0.00030160003399869303
  },
  {
    "owner": "DoBGGtypSJvgmwVj1dVKARui52YdWHHEZUmXLjmnkdum",
    "amount": 1471302.420546266,
    "percentage": 2.1785871213993167,
    "double_amount_for_100_apy": 2942604.841092532,
    "sol_equivalent_for_100_apy": 3.9963545996663736,
    "daily_sol_for_100_apy": 0.010948916711414722
  },
  {
    "owner": "H1vNWJp5rTNs61dvWN9p73dFpGanZE5QcPn22ZyjmsL3",
    "amount": 365184.975231586,
    "percentage": 0.5407367464757351,
    "double_amount_for_100_apy": 730369.950463172,
    "sol_equivalent_for_100_apy": 0.9919161656472701,
    "daily_sol_for_100_apy": 0.002717578536019918
  },
  {
    "owner": "EjL7X5YvJVZmwjtbePR6BhFR59LF51w2PgUTHAs1MbN5",
    "amount": 79444.831892898,
    "percentage": 0.11763556234709446,
    "double_amount_for_100_apy": 158889.663785796,
    "sol_equivalent_for_100_apy": 0.215788212485253,
    "daily_sol_for_100_apy": 0.0005912005821513782
  },
  {
    "owner": "GhCfaPPdUjho2gLL2FCBAVbGtXxYWP97MgdYcXV8AbQt",
    "amount": 590523.434690664,
    "percentage": 0.8743999409882818,
    "double_amount_for_100_apy": 1181046.869381328,
    "sol_equivalent_for_100_apy": 1.603980943333608,
    "daily_sol_for_100_apy": 0.004394468337900296
  },
  {
    "owner": "8evCNBNLc9tt5kw6N2BSrz25sQThBWFx6UqL6CDRpFwL",
    "amount": 85650.564724828,
    "percentage": 0.12682451591482394,
    "double_amount_for_100_apy": 171301.129449656,
    "sol_equivalent_for_100_apy": 0.23264423650917612,
    "daily_sol_for_100_apy": 0.0006373814698881538
  },
  {
    "owner": "4mVoMoUcwW48mpUNVSomjbAEopxBiKEHK5kB8xQT5ooh",
    "amount": 20472.287,
    "percentage": 0.030313727606885395,
    "double_amount_for_100_apy": 40944.574,
    "sol_equivalent_for_100_apy": 0.05560686720529146,
    "daily_sol_for_100_apy": 0.00015234758138436017
  },
  {
    "owner": "54epYFYzmidCNNLnL7MTJio3tXw6G9djAYMe8dpw56kJ",
    "amount": 27442.743139445,
    "percentage": 0.04063502237511904,
    "double_amount_for_100_apy": 54885.48627889,
    "sol_equivalent_for_100_apy": 0.07454003421816241,
    "daily_sol_for_100_apy": 0.00020421927183058195
  },
  {
    "owner": "H6bughJVtUV3emRGxpzScRGnqGJY15BFfvpfonPpQ3SE",
    "amount": 148595.114403241,
    "percentage": 0.22002777812434052,
    "double_amount_for_100_apy": 297190.228806482,
    "sol_equivalent_for_100_apy": 0.4036143491919644,
    "daily_sol_for_100_apy": 0.0011057927375122314
  },
  {
    "owner": "53cQzmcVtg55SUEHAtTC87emqZKfdAPGbz86PirMdcLZ",
    "amount": 47630.236489773,
    "percentage": 0.0705270502901074,
    "double_amount_for_100_apy": 95260.472979546,
    "sol_equivalent_for_100_apy": 0.1293733443382967,
    "daily_sol_for_100_apy": 0.00035444751873505944
  },
  {
    "owner": "6vPLQSv1zBoMxw5tWddu7uoq22swzBiJqLVXvMfTnm1z",
    "amount": 278384.870328537,
    "percentage": 0.4122100832709791,
    "double_amount_for_100_apy": 556769.740657074,
    "sol_equivalent_for_100_apy": 0.7561495457894489,
    "daily_sol_for_100_apy": 0.0020716425912039697
  },
  {
    "owner": "9aBMk5SvGaBL1iPiqVoBiBVwttc4ZsJq5AfNhkQ3g8nS",
    "amount": 84228.497480852,
    "percentage": 0.12471883231081023,
    "double_amount_for_100_apy": 168456.994961704,
    "sol_equivalent_for_100_apy": 0.22878161459532897,
    "daily_sol_for_100_apy": 0.0006267989440967918
  },
  {
    "owner": "BqhVUXVBtYeh4bdWwKJKfaffi1GstBR8hsBr9VTA2oAw",
    "amount": 41935.775725598,
    "percentage": 0.06209514756847707,
    "double_amount_for_100_apy": 83871.551451196,
    "sol_equivalent_for_100_apy": 0.11390603853512865,
    "daily_sol_for_100_apy": 0.00031207133845240724
  },
  {
    "owner": "FZjutB3bDfV8fXy6f3eYkQLbQZamF8942L9DXGCyv47c",
    "amount": 79216.834360712,
    "percentage": 0.11729796181005,
    "double_amount_for_100_apy": 158433.668721424,
    "sol_equivalent_for_100_apy": 0.21516892512886723,
    "daily_sol_for_100_apy": 0.00058950390446265
  },
  {
    "owner": "DnX5B6kqDDzpbq2B46duxJqrFNji7aP2kLBcDiGcXvbB",
    "amount": 63475.617628846,
    "percentage": 0.09398962521772239,
    "double_amount_for_100_apy": 126951.235257692,
    "sol_equivalent_for_100_apy": 0.17241260051996618,
    "daily_sol_for_100_apy": 0.00047236328909579776
  },
  {
    "owner": "7txmSTPVWVKgH8T29VyUmNGEKKDuTkBDYawxaSBhm1KC",
    "amount": 84414.101158739,
    "percentage": 0.12499365941411836,
    "double_amount_for_100_apy": 168828.202317478,
    "sol_equivalent_for_100_apy": 0.2292857516792354,
    "daily_sol_for_100_apy": 0.0006281801415869463
  },
  {
    "owner": "D7qLRacXg2H2Hg5xMjaqygfWdgeYrXf4TUmQcCf5T99s",
    "amount": 1043541.599566623,
    "percentage": 1.5451930600482537,
    "double_amount_for_100_apy": 2087083.199133246,
    "sol_equivalent_for_100_apy": 2.8344697956949627,
    "daily_sol_for_100_apy": 0.0077656706731368845
  },
  {
    "owner": "2nLBJVQjJCJAkMDw1aKGBHfM6qXdRFQA9PmZbWSMQz18",
    "amount": 84504.524927951,
    "percentage": 0.12512755171003434,
    "double_amount_for_100_apy": 169009.049855902,
    "sol_equivalent_for_100_apy": 0.22953136090339166,
    "daily_sol_for_100_apy": 0.000628853043570936
  },
  {
    "owner": "2qN1GwmgbsGb3Rsb3PAtLaLdXpMjwakgDjFJwCwHbdHd",
    "amount": 84897.804935129,
    "percentage": 0.12570988933605665,
    "double_amount_for_100_apy": 169795.609870258,
    "sol_equivalent_for_100_apy": 0.23059958885142906,
    "daily_sol_for_100_apy": 0.0006317796954833673
  },
  {
    "owner": "6tNWNPknqvToHVYhL6iDwCuFhh1YjEcZPcd4FaP9EQW1",
    "amount": 79144.835762562,
    "percentage": 0.1171913520359492,
    "double_amount_for_100_apy": 158289.671525124,
    "sol_equivalent_for_100_apy": 0.21497336239148013,
    "daily_sol_for_100_apy": 0.0005889681161410415
  },
  {
    "owner": "3fM5cdu7uDHkqGEDTBzJs3gECu6wyBNTXKpFYZwZ1TZ8",
    "amount": 1145239.999999999,
    "percentage": 1.695779929448498,
    "double_amount_for_100_apy": 2290479.999999998,
    "sol_equivalent_for_100_apy": 3.1107031958954043,
    "daily_sol_for_100_apy": 0.008522474509302477
  },
  {
    "owner": "Df9TCSZfVdaYAqvpNgbVHQcBiXvamRTWzA8BoJkAuvtA",
    "amount": 896483.999999999,
    "percentage": 1.3274419111030935,
    "double_amount_for_100_apy": 1792967.999999998,
    "sol_equivalent_for_100_apy": 2.4350316474006277,
    "daily_sol_for_100_apy": 0.006671319581919528
  },
  {
    "owner": "B4hhtcJS2H6Kkn9iK87Q6ZjSK4hECXq17zGJqBxDnzeq",
    "amount": 241564.070164203,
    "percentage": 0.35768878301521473,
    "double_amount_for_100_apy": 483128.140328406,
    "sol_equivalent_for_100_apy": 0.656136814181559,
    "daily_sol_for_100_apy": 0.001797635107346737
  },
  {
    "owner": "2ZfSrM6pVYE9LgDMhERr4irgBGEjm3ScnLEz5a6pXrCA",
    "amount": 85764.335784751,
    "percentage": 0.12699297901423498,
    "double_amount_for_100_apy": 171528.671569502,
    "sol_equivalent_for_100_apy": 0.2329532616914112,
    "daily_sol_for_100_apy": 0.0006382281142230443
  },
  {
    "owner": "w1RgmsVQkyS6FGuaLykAhwK5x3RJb8jLYnDHyJ4cp4j",
    "amount": 1009842.642830047,
    "percentage": 1.495294336219852,
    "double_amount_for_100_apy": 2019685.285660094,
    "sol_equivalent_for_100_apy": 2.742936621496709,
    "daily_sol_for_100_apy": 0.007514894853415641
  },
  {
    "owner": "Go4tyRttPra4z5Hx8vMeixBRrHtDs4DevgMuAK12jTDJ",
    "amount": 37387.911050124,
    "percentage": 0.05536103276414206,
    "double_amount_for_100_apy": 74775.822100248,
    "sol_equivalent_for_100_apy": 0.10155311933871845,
    "daily_sol_for_100_apy": 0.000278227724215667
  },
  {
    "owner": "2Rad1hnCrxuafQP3hHCGJ5fxBFnqXRUHYXVMGJofFow6",
    "amount": 83421.499458677,
    "percentage": 0.12352389408903228,
    "double_amount_for_100_apy": 166842.998917354,
    "sol_equivalent_for_100_apy": 0.22658964494122935,
    "daily_sol_for_100_apy": 0.00062079354778419
  },
  {
    "owner": "BBTD1oGYpMj9eyusWAFMfzWZgEq9ujLPNvhP2xEMJm31",
    "amount": 86524.936346108,
    "percentage": 0.12811921558148417,
    "double_amount_for_100_apy": 173049.872692216,
    "sol_equivalent_for_100_apy": 0.23501920646893648,
    "daily_sol_for_100_apy": 0.0006438882369011958
  },
  {
    "owner": "4RXTm8McowoyoQ5F2VvsgY9kJMqFhbany8XTiPFQ2Pdw",
    "amount": 165834.286065357,
    "percentage": 0.24555416674588154,
    "double_amount_for_100_apy": 331668.572130714,
    "sol_equivalent_for_100_apy": 0.4504394220010995,
    "daily_sol_for_100_apy": 0.0012340806082221903
  },
  {
    "owner": "5ai4cmkQeXyxp4CGscYXr1nVxU4A6vELKs7FJEZwpgw7",
    "amount": 101861.436134793,
    "percentage": 0.15082827964634668,
    "double_amount_for_100_apy": 203722.872269586,
    "sol_equivalent_for_100_apy": 0.2766762381011809,
    "daily_sol_for_100_apy": 0.0007580170906881669
  },
  {
    "owner": "C3gfPwiTcLPe9rSnPFJA4i8RYRUg1c3y1wwe9itCV9uD",
    "amount": 86639.608198267,
    "percentage": 0.1282890125020981,
    "double_amount_for_100_apy": 173279.216396534,
    "sol_equivalent_for_100_apy": 0.23533067838485824,
    "daily_sol_for_100_apy": 0.00064474158461605
  },
  {
    "owner": "6WBwxaSEwmqVe5yviPFMHRgVYMbdAxAG9nej78jyoELC",
    "amount": 84639.206550521,
    "percentage": 0.1253269775006282,
    "double_amount_for_100_apy": 169278.413101042,
    "sol_equivalent_for_100_apy": 0.22989718339802762,
    "daily_sol_for_100_apy": 0.0006298552969808976
  },
  {
    "owner": "98n96p8o8RZVP22BFoMScaS3VXGMgQ5zGj7Dbvy9cGji",
    "amount": 55637.541014763,
    "percentage": 0.0823836273416077,
    "double_amount_for_100_apy": 111275.082029526,
    "sol_equivalent_for_100_apy": 0.15112280102544887,
    "daily_sol_for_100_apy": 0.0004140350713025996
  },
  {
    "owner": "G91Jq6HUt4M3tZrKgrVZuemtkMp1ro5zynreT7CT98Ep",
    "amount": 360289.914020513,
    "percentage": 0.5334885307697177,
    "double_amount_for_100_apy": 720579.828041026,
    "sol_equivalent_for_100_apy": 0.9786201905211931,
    "daily_sol_for_100_apy": 0.0026811512069073785
  },
  {
    "owner": "A2S5cnnwcf8p6MQz7Y3WQc5Eok1fr8RLSBYd6YY1jmbj",
    "amount": 76217.85864454,
    "percentage": 0.11285731807739316,
    "double_amount_for_100_apy": 152435.71728908,
    "sol_equivalent_for_100_apy": 0.20702310124504467,
    "daily_sol_for_100_apy": 0.000567186578753547
  },
  {
    "owner": "HEJ79d6rV6FMBgRXwDYmYHYUPEtnGBy5Zo9uAUAqntqS",
    "amount": 829072.378522958,
    "percentage": 1.2276241657288964,
    "double_amount_for_100_apy": 1658144.757045916,
    "sol_equivalent_for_100_apy": 2.2519280652963327,
    "daily_sol_for_100_apy": 0.00616966593231872
  },
  {
    "owner": "9RBAYbLc4LkXwW4q3QJPVZTT23x5cRt7FUFPgwAiEoAe",
    "amount": 80638.513935424,
    "percentage": 0.11940307138437807,
    "double_amount_for_100_apy": 161277.027870848,
    "sol_equivalent_for_100_apy": 0.21903049405467825,
    "daily_sol_for_100_apy": 0.0006000835453552829
  },
  {
    "owner": "D29kmutt7NrAkUqUcSfNeiguf9uquKatttTGoYYGAy5D",
    "amount": 64094.264651483,
    "percentage": 0.09490566832170137,
    "double_amount_for_100_apy": 128188.529302966,
    "sol_equivalent_for_100_apy": 0.17409297080955446,
    "daily_sol_for_100_apy": 0.00047696704331384786
  },
  {
    "owner": "A8wzugnC1Kgeyackjyddz784QTG7VBekzEAeMmuLyMiu",
    "amount": 86185.825039874,
    "percentage": 0.12761708664173296,
    "double_amount_for_100_apy": 172371.650079748,
    "sol_equivalent_for_100_apy": 0.2340981116555643,
    "daily_sol_for_100_apy": 0.0006413646894672994
  },
  {
    "owner": "4cUyKneVRn7npmjLFigJvJUZwn6qr6x5Wm66UtNaiKoK",
    "amount": 48466.528595566,
    "percentage": 0.07176536485138713,
    "double_amount_for_100_apy": 96933.057191132,
    "sol_equivalent_for_100_apy": 0.13164488264135316,
    "daily_sol_for_100_apy": 0.000360670911346173
  },
  {
    "owner": "CCK7AxcYxJe65Y1yLcsVYUmaJA38HXWeEDfyWTz7KbS3",
    "amount": 33403.341498095,
    "percentage": 0.04946100039204329,
    "double_amount_for_100_apy": 66806.68299619,
    "sol_equivalent_for_100_apy": 0.09073022349176572,
    "daily_sol_for_100_apy": 0.0002485759547719609
  },
  {
    "owner": "9z3sV8EkCKNgtjpbe3c1uot9J92sn6WciBeVkMZtqVT8",
    "amount": 386903.964066464,
    "percentage": 0.5728964905940878,
    "double_amount_for_100_apy": 773807.928132928,
    "sol_equivalent_for_100_apy": 1.050909326888819,
    "daily_sol_for_100_apy": 0.002879203635311833
  },
  {
    "owner": "muMRkJg6ENSB39nBn47oN1ZguAC6JwTsFvxDfMw1MYT",
    "amount": 86781.431405828,
    "percentage": 0.12849901298139674,
    "double_amount_for_100_apy": 173562.862811656,
    "sol_equivalent_for_100_apy": 0.2357158988670385,
    "daily_sol_for_100_apy": 0.0006457969831973658
  },
  {
    "owner": "6AiKWmYLF4hN3tiBU4g14LXkiHvKo6Bnge3h7vEMbgBF",
    "amount": 59509.093544188,
    "percentage": 0.08811631313253752,
    "double_amount_for_100_apy": 119018.187088376,
    "sol_equivalent_for_100_apy": 0.1616387198078519,
    "daily_sol_for_100_apy": 0.00044284580769274497
  },
  {
    "owner": "GNXVuVWJk3TgEpBdMaphhGnJQGj3RE2dhX1SdoQzQHAM",
    "amount": 90634.357491351,
    "percentage": 0.13420411822176423,
    "double_amount_for_100_apy": 181268.714982702,
    "sol_equivalent_for_100_apy": 0.24618122446497884,
    "daily_sol_for_100_apy": 0.0006744691081232297
  },
  {
    "owner": "76QmSGCVUzk7YXmFWVCpaRKWVF1dW4PXTeVxiKnkJzDC",
    "amount": 47300.963381792,
    "percentage": 0.07003948896861906,
    "double_amount_for_100_apy": 94601.926763584,
    "sol_equivalent_for_100_apy": 0.1284789720588453,
    "daily_sol_for_100_apy": 0.0003519971837228638
  },
  {
    "owner": "2hKuLYRaiiBVa7eiiYLJiBPUVVT2qoBH7VEQjP3A2ayX",
    "amount": 78917.818687718,
    "percentage": 0.11685520328183428,
    "double_amount_for_100_apy": 157835.637375436,
    "sol_equivalent_for_100_apy": 0.2143567381553025,
    "daily_sol_for_100_apy": 0.0005872787346720617
  },
  {
    "owner": "2JruZtz6cxBEDm45tT4h37tYZdjEq2yX7cY4F8BTQNBY",
    "amount": 269471.647019959,
    "percentage": 0.3990120940343308,
    "double_amount_for_100_apy": 538943.294039918,
    "sol_equivalent_for_100_apy": 0.7319394306767013,
    "daily_sol_for_100_apy": 0.002005313508703291
  },
  {
    "owner": "CqESndD3BioCn7EfJVTh2yi9NMAzoNz2dVDDr7eDEA59",
    "amount": 87211.238422564,
    "percentage": 0.12913543688600804,
    "double_amount_for_100_apy": 174422.476845128,
    "sol_equivalent_for_100_apy": 0.23688334155204685,
    "daily_sol_for_100_apy": 0.0006489954563069776
  },
  {
    "owner": "9Gxdt1xEUutWEMsckvKxsR4iqJ53fnMLfE5RHLjyjrH2",
    "amount": 84201.00268826,
    "percentage": 0.12467812021776262,
    "double_amount_for_100_apy": 168402.00537652,
    "sol_equivalent_for_100_apy": 0.2287069331842829,
    "daily_sol_for_100_apy": 0.000626594337491186
  },
  {
    "owner": "GZtd6uxVTtuWpHfoGNbq4DDCYadPvFDvDakWVZyn6xfk",
    "amount": 86293.993701623,
    "percentage": 0.12777725415735347,
    "double_amount_for_100_apy": 172587.987403246,
    "sol_equivalent_for_100_apy": 0.23439191959258912,
    "daily_sol_for_100_apy": 0.0006421696427194222
  },
  {
    "owner": "7v1rebHZmKx84XPLs1WyvDdvHBLTjPrpoiDEUEVZLC1v",
    "amount": 237043.574339139,
    "percentage": 0.3509951938188024,
    "double_amount_for_100_apy": 474087.148678278,
    "sol_equivalent_for_100_apy": 0.6438582343117863,
    "daily_sol_for_100_apy": 0.0017639951624980447
  },
  {
    "owner": "4tCukTai7QuXKkFbFHoiQDGnmETKEAbU2m8mutzD9NLZ",
    "amount": 172442.062850298,
    "percentage": 0.2553384348907059,
    "double_amount_for_100_apy": 344884.125700596,
    "sol_equivalent_for_100_apy": 0.46838747862039276,
    "daily_sol_for_100_apy": 0.001283253366083268
  },
  {
    "owner": "9S5oDjU1FkbX1GjR5wrvkD159CY6Q8JuPEjqotQtESLA",
    "amount": 55106.572914615,
    "percentage": 0.08159741218372953,
    "double_amount_for_100_apy": 110213.14582923,
    "sol_equivalent_for_100_apy": 0.14968058440181634,
    "daily_sol_for_100_apy": 0.0004100837928816886
  },
  {
    "owner": "627L8LHowp7qzshnQJSgpoenCpJfYpyHprf5UjQsu9FT",
    "amount": 87020.407686873,
    "percentage": 0.1288528699729534,
    "double_amount_for_100_apy": 174040.815373746,
    "sol_equivalent_for_100_apy": 0.23636500672319957,
    "daily_sol_for_100_apy": 0.0006475753608854782
  },
  {
    "owner": "DCM312seeKsTPWGiZsxoPKX6KnnNVmZvdVMnbiup7AT2",
    "amount": 56711.035921556,
    "percentage": 0.08397317286682927,
    "double_amount_for_100_apy": 113422.071843112,
    "sol_equivalent_for_100_apy": 0.1540386300545942,
    "daily_sol_for_100_apy": 0.0004220236439851896
  },
  {
    "owner": "A6FAccJtbQi1g5tRfPGG6tMeJ86SSnwsmMxVR1Y5NMR5",
    "amount": 32969.082961139,
    "percentage": 0.04881798503180296,
    "double_amount_for_100_apy": 65938.165922278,
    "sol_equivalent_for_100_apy": 0.0895506895785651,
    "daily_sol_for_100_apy": 0.0002453443550097674
  },
  {
    "owner": "HvwnSN9PskkMHheJEwPAFT4Av4uNcw9Ychw8KaC1Wbbi",
    "amount": 79170.37133804,
    "percentage": 0.1172291630767638,
    "double_amount_for_100_apy": 158340.74267608,
    "sol_equivalent_for_100_apy": 0.21504272217305292,
    "daily_sol_for_100_apy": 0.000589158142939871
  },
  {
    "owner": "52JYwt7CpEuMvKbbUDHHE1UmDrpES9cnNGjSAi3d7sLk",
    "amount": 89050.02147193,
    "percentage": 0.1318581599743781,
    "double_amount_for_100_apy": 178100.04294386,
    "sol_equivalent_for_100_apy": 0.24187784777626284,
    "daily_sol_for_100_apy": 0.0006626790350034599
  },
  {
    "owner": "EbBaXL4hZzfMq8UyAbhUrKqreCWuhMkDVcp8PFqJb7x9",
    "amount": 64265.644019962,
    "percentage": 0.09515943320363725,
    "double_amount_for_100_apy": 128531.288039924,
    "sol_equivalent_for_100_apy": 0.174558471795582,
    "daily_sol_for_100_apy": 0.0004782423884810466
  },
  {
    "owner": "ABj7j2dJao3sQp7t73PnMvgztVfUbPfpyQfpykFYvnDZ",
    "amount": 356339.355432197,
    "percentage": 0.52763885911646,
    "double_amount_for_100_apy": 712678.710864394,
    "sol_equivalent_for_100_apy": 0.9678896753224167,
    "daily_sol_for_100_apy": 0.0026517525351299085
  },
  {
    "owner": "BRRr9HZxnBABesPepcTQXMXuWCt5aFEMUuhrJ4y8uEEL",
    "amount": 257244.803962953,
    "percentage": 0.3809075613105458,
    "double_amount_for_100_apy": 514489.607925906,
    "sol_equivalent_for_100_apy": 0.6987288549256447,
    "daily_sol_for_100_apy": 0.0019143256299332732
  },
  {
    "owner": "AyvWC5qage5GVdUCregpEX67nRiJV9CVb3nrAMSP9aqR",
    "amount": 121400.563618226,
    "percentage": 0.17976025916622138,
    "double_amount_for_100_apy": 242801.127236452,
    "sol_equivalent_for_100_apy": 0.3297484555470638,
    "daily_sol_for_100_apy": 0.0009034204261563391
  },
  {
    "owner": "5auQXsuxhEpumHFTSaZ5QfiipWG6xGmrtELyjD8gYfTz",
    "amount": 85459.936496612,
    "percentage": 0.12654224885866538,
    "double_amount_for_100_apy": 170919.872993224,
    "sol_equivalent_for_100_apy": 0.23212645173154053,
    "daily_sol_for_100_apy": 0.0006359628814562754
  },
  {
    "owner": "C6Kbm8TGaCYqLmJexFbowNsKRtYtSx4GsmWs3ZdWsdHq",
    "amount": 86559.926600111,
    "percentage": 0.12817102635517752,
    "double_amount_for_100_apy": 173119.853200222,
    "sol_equivalent_for_100_apy": 0.235114247067372,
    "daily_sol_for_100_apy": 0.000644148622102389
  },
  {
    "owner": "2S2e3rJwhjUEJqinGwV6RmGhVAKJXXkNpFsmhKmpcPH1",
    "amount": 78734.348615839,
    "percentage": 0.11658353545190617,
    "double_amount_for_100_apy": 157468.697231678,
    "sol_equivalent_for_100_apy": 0.21385839637633464,
    "daily_sol_for_100_apy": 0.0005859134147296839
  },
  {
    "owner": "8NtZ91dXwb1RpRK6kLpb29xPkscCvjgrsWYZJJQGPFuw",
    "amount": 92970.238061744,
    "percentage": 0.13766290361946354,
    "double_amount_for_100_apy": 185940.476123488,
    "sol_equivalent_for_100_apy": 0.25252594797756267,
    "daily_sol_for_100_apy": 0.000691851912267295
  },
  {
    "owner": "DKoTRmcy93NBbK67UgqdyUf8hSMAkP5TToj5mvm612K",
    "amount": 236146.777037078,
    "percentage": 0.34966728799502866,
    "double_amount_for_100_apy": 472293.554074156,
    "sol_equivalent_for_100_apy": 0.6414223516726962,
    "daily_sol_for_100_apy": 0.0017573215114320446
  },
  {
    "owner": "DA7iMX8acSwZGcu1PZ2KHWLpp943VQAyYxi67LqhzjCb",
    "amount": 392893.618708431,
    "percentage": 0.5817654928348195,
    "double_amount_for_100_apy": 785787.237416862,
    "sol_equivalent_for_100_apy": 1.0671784388977226,
    "daily_sol_for_100_apy": 0.002923776544925267
  },
  {
    "owner": "FRTT1miwwfTHch5sVFSoV9EY8fgcN1s8aq6ZgBWWBmWr",
    "amount": 140670.814103162,
    "percentage": 0.20829410710010393,
    "double_amount_for_100_apy": 281341.628206324,
    "sol_equivalent_for_100_apy": 0.38209034874778625,
    "daily_sol_for_100_apy": 0.001046822873281606
  },
  {
    "owner": "93SXE6KMNrXXZpovjha15yoJSfAc6YFgj8rRE38UMUBs",
    "amount": 47674.684297086,
    "percentage": 0.07059286505343157,
    "double_amount_for_100_apy": 95349.368594172,
    "sol_equivalent_for_100_apy": 0.12949407356209178,
    "daily_sol_for_100_apy": 0.0003547782837317583
  },
  {
    "owner": "4EG5qw8sKMURwTJ3s7w5Z6Un3VTtPiJ8DYKKobjxMAGw",
    "amount": 85701.363989273,
    "percentage": 0.12689973540862137,
    "double_amount_for_100_apy": 171402.727978546,
    "sol_equivalent_for_100_apy": 0.23278221757363265,
    "daily_sol_for_100_apy": 0.0006377595002017333
  },
  {
    "owner": "6zuPCYF33Xwh4AhsC4QZiXWYffe3y1hNJvhdKxTAqZQj",
    "amount": 83793.951812722,
    "percentage": 0.12407539178965866,
    "double_amount_for_100_apy": 167587.903625444,
    "sol_equivalent_for_100_apy": 0.22760130077585491,
    "daily_sol_for_100_apy": 0.000623565207605082
  },
  {
    "owner": "FzKviPkXJD3cmu9FNjaC5QWUXJqKPrzkcGDXKBoFvH5d",
    "amount": 3640031.904252713,
    "percentage": 5.389868539156817,
    "double_amount_for_100_apy": 7280063.808505426,
    "sol_equivalent_for_100_apy": 9.887061993748173,
    "daily_sol_for_100_apy": 0.027087841078762116
  },
  {
    "owner": "H3NHCLKceUp2LiQbsfekm6y2mtz6RAyUGg45HrApHQaZ",
    "amount": 341767.936273206,
    "percentage": 0.5060626653462476,
    "double_amount_for_100_apy": 683535.872546412,
    "sol_equivalent_for_100_apy": 0.9283107572383428,
    "daily_sol_for_100_apy": 0.002543317143118747
  },
  {
    "owner": "Baw2AgUDqwiRdPmgn6nuajvRtAK2LjCwU58SzZYhNi2V",
    "amount": 379458.962549616,
    "percentage": 0.5618725269297166,
    "double_amount_for_100_apy": 758917.925099232,
    "sol_equivalent_for_100_apy": 1.030687198765539,
    "daily_sol_for_100_apy": 0.0028238005445631207
  },
  {
    "owner": "4v91uQbk67t28xULRseArTsHJ8aMeSx5UUNpzuD5GQRe",
    "amount": 217677.069070252,
    "percentage": 0.32231881948806196,
    "double_amount_for_100_apy": 435354.138140504,
    "sol_equivalent_for_100_apy": 0.5912548936729228,
    "daily_sol_for_100_apy": 0.0016198764210217063
  },
  {
    "owner": "Dn2w1i6ESwTM2SgdZ6H7GpSZhLn5LiMMPSVrBtoirNDt",
    "amount": 285965.968601737,
    "percentage": 0.42343556814303146,
    "double_amount_for_100_apy": 571931.937203474,
    "sol_equivalent_for_100_apy": 0.7767413401965954,
    "daily_sol_for_100_apy": 0.0021280584662920423
  },
  {
    "owner": "AS4JELgGLuBjcU81hXw2LeTyn1mv8Mf1YVL1YAAa63x2",
    "amount": 60070.628590622,
    "percentage": 0.08894778938330129,
    "double_amount_for_100_apy": 120141.257181244,
    "sol_equivalent_for_100_apy": 0.16316396243258519,
    "daily_sol_for_100_apy": 0.00044702455460982244
  },
  {
    "owner": "JD8vN6oQ81qwqf3n4DHKEngMi5yXCas8En3E1HUE7Vj5",
    "amount": 85736.87833986,
    "percentage": 0.1269523222226803,
    "double_amount_for_100_apy": 171473.75667972,
    "sol_equivalent_for_100_apy": 0.23287868172426585,
    "daily_sol_for_100_apy": 0.0006380237855459338
  },
  {
    "owner": "GMRKKmAJDfBKmJnPLWSxrCRSMru7pKi28nMrUpFgTJRn",
    "amount": 300457.248767229,
    "percentage": 0.4448930984918286,
    "double_amount_for_100_apy": 600914.497534458,
    "sol_equivalent_for_100_apy": 0.8161025845850306,
    "daily_sol_for_100_apy": 0.0022358974920137823
  },
  {
    "owner": "JDTybisdWYmqxsGAmX9Y4PgaFkN9oP5qrH1nsKfMQJta",
    "amount": 286670.579,
    "percentage": 0.4244788989483257,
    "double_amount_for_100_apy": 573341.158,
    "sol_equivalent_for_100_apy": 0.778655204380293,
    "daily_sol_for_100_apy": 0.002133301929809022
  },
  {
    "owner": "EuedL84fVmM5FL7FWmWV9u5TMgf5nL9V9vd4jtyu9k1r",
    "amount": 85060.796427826,
    "percentage": 0.1259512341214173,
    "double_amount_for_100_apy": 170121.592855652,
    "sol_equivalent_for_100_apy": 0.23104230667235423,
    "daily_sol_for_100_apy": 0.0006329926210201486
  },
  {
    "owner": "CDB5mDxYAvhzEdb5rG7SaHCSv4hLAEeuAM9ZMvTjpRuP",
    "amount": 22225.982346468,
    "percentage": 0.03291045962018189,
    "double_amount_for_100_apy": 44451.964692936,
    "sol_equivalent_for_100_apy": 0.06037025803942659,
    "daily_sol_for_100_apy": 0.00016539796723130573
  },
  {
    "owner": "23oKdX41ZMyZrPjVtuj1KoqJMg4y1LuiZkLBKUDr6UVP",
    "amount": 93506.304657661,
    "percentage": 0.13845666822269417,
    "double_amount_for_100_apy": 187012.609315322,
    "sol_equivalent_for_100_apy": 0.2539820131456775,
    "daily_sol_for_100_apy": 0.0006958411319059656
  },
  {
    "owner": "AJYhaQxosfrhQK4iaTqD8VsYNM5KQKJhQVfdYQmtuLfJ",
    "amount": 94296.162317094,
    "percentage": 0.1396262263642083,
    "double_amount_for_100_apy": 188592.324634188,
    "sol_equivalent_for_100_apy": 0.2561274261119559,
    "daily_sol_for_100_apy": 0.0007017189756491942
  },
  {
    "owner": "2iMbbqGkfxoYutXnwbBikTSh1AWrZLFcWy2e9mqWaTei",
    "amount": 85607.169702613,
    "percentage": 0.12676026003159407,
    "double_amount_for_100_apy": 171214.339405226,
    "sol_equivalent_for_100_apy": 0.23252636686238579,
    "daily_sol_for_100_apy": 0.0006370585393490021
  },
  {
    "owner": "7ftDeYapdZ9xHQ2X8XX14x5gSdcacPeeBi23xDAozMct",
    "amount": 86026.036123294,
    "percentage": 0.12738048397531834,
    "double_amount_for_100_apy": 172052.072246588,
    "sol_equivalent_for_100_apy": 0.23366409267834198,
    "daily_sol_for_100_apy": 0.0006401755963790192
  },
  {
    "owner": "6ecsPGq1GCM7wLUeBkzXuscfVoEwxuiTPopaRS5Eokki",
    "amount": 85843.601296469,
    "percentage": 0.12711034905358817,
    "double_amount_for_100_apy": 171687.202592938,
    "sol_equivalent_for_100_apy": 0.23316856283407603,
    "daily_sol_for_100_apy": 0.0006388179803673316
  },
  {
    "owner": "AJwVgVuETmuu8uRw5Fi4LeJYZTynHR8VTcvBHhgkN5Kr",
    "amount": 800201.638325784,
    "percentage": 1.1848746793551321,
    "double_amount_for_100_apy": 1600403.276651568,
    "sol_equivalent_for_100_apy": 2.173509302592257,
    "daily_sol_for_100_apy": 0.0059548200071020746
  },
  {
    "owner": "8TnnKg7QkWfa1V8Mp7utZMEAk8XKMqqpC2TSVvxtW5Ht",
    "amount": 70714.356027049,
    "percentage": 0.10470817092884044,
    "double_amount_for_100_apy": 141428.712054098,
    "sol_equivalent_for_100_apy": 0.19207447634471983,
    "daily_sol_for_100_apy": 0.0005262314420403283
  },
  {
    "owner": "ButcZhoUCaY8gbKRGcPkdgxTJS3tHpqUAMdaE5kGYzbF",
    "amount": 89120.234248345,
    "percentage": 0.1319621254462752,
    "double_amount_for_100_apy": 178240.46849669,
    "sol_equivalent_for_100_apy": 0.24206855986105455,
    "daily_sol_for_100_apy": 0.0006632015338659029
  },
  {
    "owner": "4aYHhiJYGibcN28cpVL24SNRCRtsHrexwKiU1pynM5pc",
    "amount": 427352.402364457,
    "percentage": 0.6327893076833202,
    "double_amount_for_100_apy": 854704.804728914,
    "sol_equivalent_for_100_apy": 1.1607754565057946,
    "daily_sol_for_100_apy": 0.003180206730152862
  },
  {
    "owner": "HXaE7of4dzmG4EnUb33xHfhmtLRBuuaUdixUzGFyiWWP",
    "amount": 85736.808675526,
    "percentage": 0.1269522190692981,
    "double_amount_for_100_apy": 171473.617351052,
    "sol_equivalent_for_100_apy": 0.23287849250186143,
    "daily_sol_for_100_apy": 0.0006380232671283875
  },
  {
    "owner": "3B9jAmdtCHW8a35G8HqC78dinLfoxUtc3pasqMqfNDjo",
    "amount": 85881.355674326,
    "percentage": 0.12716625272113272,
    "double_amount_for_100_apy": 171762.711348652,
    "sol_equivalent_for_100_apy": 0.23327111135129405,
    "daily_sol_for_100_apy": 0.0006390989352090247
  },
  {
    "owner": "9EkAmGeJ3aFBijxKdWAZ6HWPBXeortX9BT8Wmu7J1dJD",
    "amount": 84798.624545684,
    "percentage": 0.12556303093623153,
    "double_amount_for_100_apy": 169597.249091368,
    "sol_equivalent_for_100_apy": 0.23033019487774956,
    "daily_sol_for_100_apy": 0.0006310416298020535
  },
  {
    "owner": "BBqdZKN15A1oj15xHoy5FcaZeRpaSxEnkVpwDns9mycM",
    "amount": 86374.065637515,
    "percentage": 0.1278958182852199,
    "double_amount_for_100_apy": 172748.13127503,
    "sol_equivalent_for_100_apy": 0.2346094111462205,
    "daily_sol_for_100_apy": 0.0006427655099896452
  },
  {
    "owner": "8ccAjDpyEv5CiEBV8YUJYVzMQ9NGWdNR7sYWSPPa3Air",
    "amount": 94240.98253752,
    "percentage": 0.13954452055344987,
    "double_amount_for_100_apy": 188481.96507504,
    "sol_equivalent_for_100_apy": 0.25597754668347833,
    "daily_sol_for_100_apy": 0.0007013083470780228
  },
  {
    "owner": "DS2mRtamRNUxzc66FPFLPYB5cUYd57tmSkJjDCR9bBdi",
    "amount": 84704.829476042,
    "percentage": 0.1254241466878817,
    "double_amount_for_100_apy": 169409.658952084,
    "sol_equivalent_for_100_apy": 0.2300754285205715,
    "daily_sol_for_100_apy": 0.0006303436397823877
  },
  {
    "owner": "45uHGcerR18ZqTVZGtZkxL8MZXMkLjsMqqdNUSGQaerZ",
    "amount": 2185881.548879351,
    "percentage": 3.2366788260464205,
    "double_amount_for_100_apy": 4371763.097758702,
    "sol_equivalent_for_100_apy": 5.937295868069399,
    "daily_sol_for_100_apy": 0.016266564022107945
  },
  {
    "owner": "6QyRXcK21uo3dXZwbFm1N6Dupi4XN3BpTDkWwPei65fC",
    "amount": 89555.373726999,
    "percentage": 0.1326064452346271,
    "double_amount_for_100_apy": 179110.747453998,
    "sol_equivalent_for_100_apy": 0.24325048658987053,
    "daily_sol_for_100_apy": 0.0006664396892873165
  },
  {
    "owner": "42eK9KwtLnibpzACAcDace7wxNp8evxhBAg8oVHLW3EC",
    "amount": 55233.914159167,
    "percentage": 0.08178596892878058,
    "double_amount_for_100_apy": 110467.828318334,
    "sol_equivalent_for_100_apy": 0.15002646894688743,
    "daily_sol_for_100_apy": 0.0004110314217722943
  },
  {
    "owner": "7m7TfFwKWuWtVuy4emWNChY8SJPwGjBZ6iLT2betFPJ5",
    "amount": 1195664.328999999,
    "percentage": 1.770444248782531,
    "double_amount_for_100_apy": 2391328.657999998,
    "sol_equivalent_for_100_apy": 3.2476658599406534,
    "daily_sol_for_100_apy": 0.008897714684768913
  },
  {
    "owner": "ZY7KnsopGG7TwkU8Km5QkhyU6Xwn46qGuWU6HV3wUQc",
    "amount": 84491.828263395,
    "percentage": 0.12510875150315628,
    "double_amount_for_100_apy": 168983.65652679,
    "sol_equivalent_for_100_apy": 0.22949687419753823,
    "daily_sol_for_100_apy": 0.0006287585594453102
  },
  {
    "owner": "9GReid1CpJaJuEto7jarjLDeGWASYDDAwZxBeWEbnKq1",
    "amount": 1224478.733450482,
    "percentage": 1.8131103176817491,
    "double_amount_for_100_apy": 2448957.466900964,
    "sol_equivalent_for_100_apy": 3.325931603376038,
    "daily_sol_for_100_apy": 0.009112141379112433
  },
  {
    "owner": "3GL5LyxFbF7GXhnAKcNRkbUEJ3iXZduZYR96etnNrPx5",
    "amount": 84037.929956283,
    "percentage": 0.12443665513976418,
    "double_amount_for_100_apy": 168075.859912566,
    "sol_equivalent_for_100_apy": 0.22826399470106168,
    "daily_sol_for_100_apy": 0.000625380807400169
  },
  {
    "owner": "68AT5oxAdKtbRXa9Y9wacyJSwDw5s51EmuuRDrH6veB5",
    "amount": 85509.564389119,
    "percentage": 0.12661573387844655,
    "double_amount_for_100_apy": 171019.128778238,
    "sol_equivalent_for_100_apy": 0.2322612511131785,
    "daily_sol_for_100_apy": 0.000636332194830626
  },
  {
    "owner": "AFYVx1QHny6YjVa6Ks4rbwMgA3vcYvMCCMF793vbMPFR",
    "amount": 48263.055218606,
    "percentage": 0.07146407772482337,
    "double_amount_for_100_apy": 96526.110437212,
    "sol_equivalent_for_100_apy": 0.13109220784481349,
    "daily_sol_for_100_apy": 0.0003591567338214068
  },
  {
    "owner": "48UZG62TRGSEfSELMTqMP5z5WWi5buBQtzMjvyvrjG9s",
    "amount": 89134.756998523,
    "percentage": 0.13198362957490523,
    "double_amount_for_100_apy": 178269.513997046,
    "sol_equivalent_for_100_apy": 0.24210800658435433,
    "daily_sol_for_100_apy": 0.0006633096070804228
  },
  {
    "owner": "9ZjwoXzhvbRYnBAHs4ySrfmcXEkYNknZ7b5XXnLXdovR",
    "amount": 349127.42673805,
    "percentage": 0.516960011073999,
    "double_amount_for_100_apy": 698254.8534761,
    "sol_equivalent_for_100_apy": 0.9483006200698471,
    "daily_sol_for_100_apy": 0.002598083890602321
  },
  {
    "owner": "CQv7EXrj7N9g9ciKeQeJDkPC7SyXawTPV3T6vGEAmpLp",
    "amount": 85085.530344638,
    "percentage": 0.12598785813010233,
    "double_amount_for_100_apy": 170171.060689276,
    "sol_equivalent_for_100_apy": 0.23110948898704292,
    "daily_sol_for_100_apy": 0.0006331766821562819
  },
  {
    "owner": "BwY5q84jD6z4rPMRqfekwSotuHhPCsJ365HTpzojjtLs",
    "amount": 86045.673935605,
    "percentage": 0.12740956207944956,
    "double_amount_for_100_apy": 172091.34787121,
    "sol_equivalent_for_100_apy": 0.23371743294371536,
    "daily_sol_for_100_apy": 0.0006403217340923709
  },
  {
    "owner": "B3bBT3W4r8MfvcanKw7QQ17GYrXKT6qXRbmkjrojbyCy",
    "amount": 111275.489534776,
    "percentage": 0.1647678580844449,
    "double_amount_for_100_apy": 222550.979069552,
    "sol_equivalent_for_100_apy": 0.30224670891747896,
    "daily_sol_for_100_apy": 0.0008280731751163807
  },
  {
    "owner": "E4KTvsgSjLj3aCxLhRUyVzujNjx8VJieHjy3sDijN4hx",
    "amount": 61455.000003585,
    "percentage": 0.09099765601126131,
    "double_amount_for_100_apy": 122910.00000717,
    "sol_equivalent_for_100_apy": 0.16692419485426993,
    "daily_sol_for_100_apy": 0.00045732656124457515
  },
  {
    "owner": "ANtrL5Bo5bpyWy2ympjK9AgHshjwvf56fWsY2A6W7ZY5",
    "amount": 68197.640058237,
    "percentage": 0.10098161891525907,
    "double_amount_for_100_apy": 136395.280116474,
    "sol_equivalent_for_100_apy": 0.18523856735852962,
    "daily_sol_for_100_apy": 0.0005075029242699442
  },
  {
    "owner": "ErkiFz9HFtVXG99EzdZ3cvXvHzHqKQYJnkpnQ8f3852f",
    "amount": 30722.499385908,
    "percentage": 0.04549142349299416,
    "double_amount_for_100_apy": 61444.998771816,
    "sol_equivalent_for_100_apy": 0.08344851474419221,
    "daily_sol_for_100_apy": 0.00022862606779230742
  },
  {
    "owner": "CzX9GsBrdBQXAyTfSJyi3eKF4N9JDwj5VSZ5B6pFFZ5B",
    "amount": 1145844.999999999,
    "percentage": 1.6966757651312514,
    "double_amount_for_100_apy": 2291689.999999998,
    "sol_equivalent_for_100_apy": 3.1123464981146043,
    "daily_sol_for_100_apy": 0.008526976707163299
  },
  {
    "owner": "J9fPCLypwGiGr3ZMsuPr9zLov2UamdzxUicmDZURpuU2",
    "amount": 85668.540877467,
    "percentage": 0.12685113356601838,
    "double_amount_for_100_apy": 171337.081754934,
    "sol_equivalent_for_100_apy": 0.23269306337119985,
    "daily_sol_for_100_apy": 0.0006375152421128764
  },
  {
    "owner": "JA2SRHpThp4hQNM9537n9138RqiKmSddt6grWFK6viYS",
    "amount": 86478.892179776,
    "percentage": 0.12805103705721502,
    "double_amount_for_100_apy": 172957.784359552,
    "sol_equivalent_for_100_apy": 0.23489414121155697,
    "daily_sol_for_100_apy": 0.0006435455923604301
  },
  {
    "owner": "4dUQNcV61gN9Geh5y2wQuwu4sxkdiQxixx4DCVSbos7T",
    "amount": 84182.248823332,
    "percentage": 0.12465035099232123,
    "double_amount_for_100_apy": 168364.497646664,
    "sol_equivalent_for_100_apy": 0.22865599389857255,
    "daily_sol_for_100_apy": 0.0006264547778043084
  },
  {
    "owner": "36to2vW2mmkovE9MVNyZ24CEueEW5TFgcS269DPMjfvD",
    "amount": 89699.280902996,
    "percentage": 0.13281953148795336,
    "double_amount_for_100_apy": 179398.561805992,
    "sol_equivalent_for_100_apy": 0.24364136755131632,
    "daily_sol_for_100_apy": 0.0006675105960310036
  },
  {
    "owner": "79WURBWJWgF2aEohjfMudtdo3JhEpU51NoHi2QU4WqyM",
    "amount": 48255.306119238,
    "percentage": 0.07145260347734723,
    "double_amount_for_100_apy": 96510.612238476,
    "sol_equivalent_for_100_apy": 0.13107115972549407,
    "daily_sol_for_100_apy": 0.00035909906774107966
  },
  {
    "owner": "xbXkY8XSL465uUveXhjsb86funRwce1r5D87ihgtAec",
    "amount": 471673.027842823,
    "percentage": 0.698415750303921,
    "double_amount_for_100_apy": 943346.055685646,
    "sol_equivalent_for_100_apy": 1.281159228745357,
    "daily_sol_for_100_apy": 0.0035100252842338547
  },
  {
    "owner": "ECAe8bm8xnQQN3MKqfRnzsURwxJ27nhN5h6Fkm9jZ4id",
    "amount": 47888.697959277,
    "percentage": 0.07090975939258432,
    "double_amount_for_100_apy": 95777.395918554,
    "sol_equivalent_for_100_apy": 0.13007537790261675,
    "daily_sol_for_100_apy": 0.00035637089836333354
  },
  {
    "owner": "3n3pCV1pkWvjzhXYDM9TM95rzBa8RBQmz1LJGauHrVbT",
    "amount": 826310.139232208,
    "percentage": 1.2235340623884716,
    "double_amount_for_100_apy": 1652620.278464416,
    "sol_equivalent_for_100_apy": 2.244425265368314,
    "daily_sol_for_100_apy": 0.006149110316077573
  },
  {
    "owner": "BVMZDy2pZAe8u4jWAEpV4H3VDPiNmz594USLHnkyU4Zt",
    "amount": 79406.628654359,
    "percentage": 0.11757899404249945,
    "double_amount_for_100_apy": 158813.257308718,
    "sol_equivalent_for_100_apy": 0.21568444477174595,
    "daily_sol_for_100_apy": 0.0005909162870458793
  },
  {
    "owner": "4aoDxFK1BXADhEfmq2gXbXVQkNQd5GPNAExs6PBTnaGh",
    "amount": 88494.228081678,
    "percentage": 0.13103518550954152,
    "double_amount_for_100_apy": 176988.456163356,
    "sol_equivalent_for_100_apy": 0.24036820064962175,
    "daily_sol_for_100_apy": 0.0006585430154784158
  },
  {
    "owner": "9kcdtMJQMvBDnMxDEGgAjZUaE7XahubFzmQJMjMX172P",
    "amount": 85298.067513827,
    "percentage": 0.12630256619633518,
    "double_amount_for_100_apy": 170596.135027654,
    "sol_equivalent_for_100_apy": 0.23168678287430045,
    "daily_sol_for_100_apy": 0.0006347583092446588
  },
  {
    "owner": "5tZyijHeRDimLDRMLwh7TgRSCT4iVLa1RsXHMsD3N6ay",
    "amount": 372860.919962814,
    "percentage": 0.5521026724080921,
    "double_amount_for_100_apy": 745721.839925628,
    "sol_equivalent_for_100_apy": 1.0127655821948474,
    "daily_sol_for_100_apy": 0.0027747002251913627
  },
  {
    "owner": "3HhWTLVug55hpRWU6FsxDGCHDKBmmYSXaySUbMoDoYqD",
    "amount": 85705.112409719,
    "percentage": 0.1269052857702569,
    "double_amount_for_100_apy": 171410.224819438,
    "sol_equivalent_for_100_apy": 0.23279239904080193,
    "daily_sol_for_100_apy": 0.0006377873946323341
  },
  {
    "owner": "47MD734cLCRpwic4wcYTTtXmrUy6Z1xUpP7CFH6PjcSt",
    "amount": 84721.947393905,
    "percentage": 0.12544949353356125,
    "double_amount_for_100_apy": 169443.89478781,
    "sol_equivalent_for_100_apy": 0.23012192424356712,
    "daily_sol_for_100_apy": 0.0006304710253248415
  },
  {
    "owner": "GwGSoymm1cE4MkZjVj4faFcXhDWUqm1nP5CAVqT9QveA",
    "amount": 223342.229642985,
    "percentage": 0.33070733682621256,
    "double_amount_for_100_apy": 446684.45928597,
    "sol_equivalent_for_100_apy": 0.6066426142370501,
    "daily_sol_for_100_apy": 0.001662034559553562
  },
  {
    "owner": "Z2x1gARyVRqmoqjTxUhyC13eupAXcHJWiQLxGzgW8R3",
    "amount": 85225.697066079,
    "percentage": 0.12619540581704675,
    "double_amount_for_100_apy": 170451.394132158,
    "sol_equivalent_for_100_apy": 0.23149021011828588,
    "daily_sol_for_100_apy": 0.0006342197537487285
  },
  {
    "owner": "EemYx31Vm5LqLQDdLKsL2KFYmkpRwjaKx1JfvUG3Foyg",
    "amount": 141347.919692611,
    "percentage": 0.20929671098112887,
    "double_amount_for_100_apy": 282695.839385222,
    "sol_equivalent_for_100_apy": 0.3839295043143554,
    "daily_sol_for_100_apy": 0.0010518616556557682
  },
  {
    "owner": "8gQjeMVhKVj3RbjEQHvxFADNTXhq9QbMVvAYPe9uZSSy",
    "amount": 85997.61800038,
    "percentage": 0.12733840468847002,
    "double_amount_for_100_apy": 171995.23600076,
    "sol_equivalent_for_100_apy": 0.23358690331561457,
    "daily_sol_for_100_apy": 0.0006399641186729167
  },
  {
    "owner": "596PuCJq33Bn6J5ZRyVdTU9zD27K6rqfHUMGQVMPiKDi",
    "amount": 1195596.722364975,
    "percentage": 1.7703441422766708,
    "double_amount_for_100_apy": 2391193.44472995,
    "sol_equivalent_for_100_apy": 3.2474822266623597,
    "daily_sol_for_100_apy": 0.008897211579896876
  },
  {
    "owner": "EAdq2omMxJhLmriAy2oZxyhS9q5bip6K3YdKTTGm6BXw",
    "amount": 33745.170673797,
    "percentage": 0.049967153735844934,
    "double_amount_for_100_apy": 67490.341347594,
    "sol_equivalent_for_100_apy": 0.09165870058766398,
    "daily_sol_for_100_apy": 0.00025111972763743555
  },
  {
    "owner": "2YG3BRuKEBGQgiG32ZRcZm8u7g8zKzKU82ZxwQqx2Cpo",
    "amount": 89469.20141799,
    "percentage": 0.13247884816144445,
    "double_amount_for_100_apy": 178938.40283598,
    "sol_equivalent_for_100_apy": 0.24301642519048527,
    "daily_sol_for_100_apy": 0.0006657984251794117
  },
  {
    "owner": "QDZkCqMUkEcUB7JdCpAc3guZQieAJ5aiW8UkC7AZkHu",
    "amount": 1195326.999999999,
    "percentage": 1.7699447589395103,
    "double_amount_for_100_apy": 2390653.999999998,
    "sol_equivalent_for_100_apy": 3.246749606231066,
    "daily_sol_for_100_apy": 0.008895204400633058
  },
  {
    "owner": "AEy1bDga7DXu5rXGemtXch9ZBw6hXeJhjzhm5ymNjgtV",
    "amount": 86498.558355745,
    "percentage": 0.12808015715998583,
    "double_amount_for_100_apy": 172997.11671149,
    "sol_equivalent_for_100_apy": 0.2349475585183554,
    "daily_sol_for_100_apy": 0.0006436919411461792
  },
  {
    "owner": "BaX37KNmPPaj5AspazbvygAfkhKZ4PLiezrDYV6P5mL4",
    "amount": 354991.449481898,
    "percentage": 0.5256429876333637,
    "double_amount_for_100_apy": 709982.898963796,
    "sol_equivalent_for_100_apy": 0.9642284904639054,
    "daily_sol_for_100_apy": 0.0026417218916819324
  },
  {
    "owner": "9FDj7xq89xw6XHQfLC46b547RpiqtsB2LNk346KmiUtZ",
    "amount": 35754.923938311,
    "percentage": 0.05294303586457467,
    "double_amount_for_100_apy": 71509.847876622,
    "sol_equivalent_for_100_apy": 0.0971175964548053,
    "daily_sol_for_100_apy": 0.000266075606725494
  },
  {
    "owner": "DzMgK5k9t2vnAHctiojF3wZRp1euZEveJAcyKYZgkjxs",
    "amount": 118629.615952422,
    "percentage": 0.17565726115949562,
    "double_amount_for_100_apy": 237259.231904844,
    "sol_equivalent_for_100_apy": 0.3222220019131744,
    "daily_sol_for_100_apy": 0.0008828000052415737
  },
  {
    "owner": "3t35yLb3PmKYVwEULLnQSgpwGrr9P2K5MbSGVj6LzDvt",
    "amount": 85746.696418277,
    "percentage": 0.12696686004909685,
    "double_amount_for_100_apy": 171493.392836554,
    "sol_equivalent_for_100_apy": 0.23290534960864753,
    "daily_sol_for_100_apy": 0.0006380968482428699
  },
  {
    "owner": "FG4662UCtZFjqpe33s71sN2iyxqZAxpA27arf6bUD4AG",
    "amount": 87009.68807911,
    "percentage": 0.1288369972338803,
    "double_amount_for_100_apy": 174019.37615822,
    "sol_equivalent_for_100_apy": 0.23633589010299147,
    "daily_sol_for_100_apy": 0.0006474955893232643
  },
  {
    "owner": "B2bdRh5atvnTRL8ELJLkbu8TM7nuEDLQ8Ud1rD9wX5vA",
    "amount": 87024.772056437,
    "percentage": 0.12885933238285116,
    "double_amount_for_100_apy": 174049.544112874,
    "sol_equivalent_for_100_apy": 0.2363768612326044,
    "daily_sol_for_100_apy": 0.0006476078389934367
  },
  {
    "owner": "7uieVDziL6ash997w57dzc5ct5VAhky1d4a2WL1Dhmuu",
    "amount": 85348.853435542,
    "percentage": 0.12637776593328362,
    "double_amount_for_100_apy": 170697.706871084,
    "sol_equivalent_for_100_apy": 0.23182472769720686,
    "daily_sol_for_100_apy": 0.0006351362402663202
  },
  {
    "owner": "7WRiimDiPyFvCmVnsdDSg5L9xEXhJxvVYaPCrJxehPAH",
    "amount": 1252836.725569478,
    "percentage": 1.8551005676510586,
    "double_amount_for_100_apy": 2505673.451138956,
    "sol_equivalent_for_100_apy": 3.4029576387168734,
    "daily_sol_for_100_apy": 0.009323171612922941
  },
  {
    "owner": "CLaHgfzRzVfkEZESRjVg1yCxMR1Jpuu2P34jv9f58piR",
    "amount": 80769.461583073,
    "percentage": 0.1195969682031162,
    "double_amount_for_100_apy": 161538.923166146,
    "sol_equivalent_for_100_apy": 0.2193861743191091,
    "daily_sol_for_100_apy": 0.0006010580118331756
  },
  {
    "owner": "C6Bym8Nz9T8pC1UW3PsWQWdyzhUNWKSP3b5mzn4QgPko",
    "amount": 824028.135740205,
    "percentage": 1.2201550538656554,
    "double_amount_for_100_apy": 1648056.27148041,
    "sol_equivalent_for_100_apy": 2.2382268828846263,
    "daily_sol_for_100_apy": 0.006132128446259251
  },
  {
    "owner": "8b8Lm5n7deoZD9bNNcWqoRmpG1ZzoNfwA6Jbe3bNsBBx",
    "amount": 130328.587843564,
    "percentage": 0.19298016441835905,
    "double_amount_for_100_apy": 260657.175687128,
    "sol_equivalent_for_100_apy": 0.35399877293974175,
    "daily_sol_for_100_apy": 0.0009698596518897035
  },
  {
    "owner": "z4YDgTE1LGe6N6qByLdBRmKc1Wym9DMSGry7vC7Xbtz",
    "amount": 79769.343861369,
    "percentage": 0.11811607375343632,
    "double_amount_for_100_apy": 159538.687722738,
    "sol_equivalent_for_100_apy": 0.21666965254797263,
    "daily_sol_for_100_apy": 0.0005936154864328017
  },
  {
    "owner": "12jXbYZNKgSsfatkD1FWRC9EG7Qr9akqU2vv8wneFkMe",
    "amount": 545473.4102416,
    "percentage": 0.8076934626240201,
    "double_amount_for_100_apy": 1090946.8204832,
    "sol_equivalent_for_100_apy": 1.4816159761399457,
    "daily_sol_for_100_apy": 0.004059221852438208
  },
  {
    "owner": "E3AR3YNiNyi9rSqmt99Fmf8XnXwgEZsADTxz2koaR3fR",
    "amount": 159551.586884024,
    "percentage": 0.23625124755473642,
    "double_amount_for_100_apy": 319103.173768048,
    "sol_equivalent_for_100_apy": 0.43337434182382484,
    "daily_sol_for_100_apy": 0.00118732696390089
  },
  {
    "owner": "34tZBEPjP3sdmQ7JesP1sesBfWNMUeFkFphY7CwdatQK",
    "amount": 852906.736399466,
    "percentage": 1.2629161793839165,
    "double_amount_for_100_apy": 1705813.472798932,
    "sol_equivalent_for_100_apy": 2.316666996191663,
    "daily_sol_for_100_apy": 0.006347032866278529
  },
  {
    "owner": "FpGFCJa5FnPRWRDrLgF2M6F6Wh3H9akLNdXv8gqdwhVo",
    "amount": 59639.593083842,
    "percentage": 0.08830954642874402,
    "double_amount_for_100_apy": 119279.186167684,
    "sol_equivalent_for_100_apy": 0.16199318292044368,
    "daily_sol_for_100_apy": 0.00044381693950806486
  },
  {
    "owner": "2uep9rqRhLqnoPa3QJHsx9r97VNzt9vmdWc2YNgo77aj",
    "amount": 37088.181711014,
    "percentage": 0.05491721749613744,
    "double_amount_for_100_apy": 74176.363422028,
    "sol_equivalent_for_100_apy": 0.10073899390381127,
    "daily_sol_for_100_apy": 0.00027599724357208567
  },
  {
    "owner": "3cQNE1dT2ea8rXMokAWfrQposyQjEGjUdCGaTfCcmK2j",
    "amount": 486947.575437906,
    "percentage": 0.7210330805081993,
    "double_amount_for_100_apy": 973895.150875812,
    "sol_equivalent_for_100_apy": 1.3226479857044933,
    "daily_sol_for_100_apy": 0.0036236931115191597
  },
  {
    "owner": "5mxsR8Bt4DqsYxVkkdyaurXAJ9T94xnXTjbtPPmJ74bq",
    "amount": 48085.227837768,
    "percentage": 0.07120076514114529,
    "double_amount_for_100_apy": 96170.455675536,
    "sol_equivalent_for_100_apy": 0.13060919275462235,
    "daily_sol_for_100_apy": 0.0003578334048071845
  },
  {
    "owner": "Bu9RTZsdUDE5VdVYcY7TuChkDdN2hqQKaqtqqPv8P6v",
    "amount": 84627.894671804,
    "percentage": 0.12531022777402712,
    "double_amount_for_100_apy": 169255.789343608,
    "sol_equivalent_for_100_apy": 0.2298664580502607,
    "daily_sol_for_100_apy": 0.0006297711179459197
  },
  {
    "owner": "7hs4RpVKnaw4BnR69izpBuMgMzyNzVePGN3rMNRgHTRX",
    "amount": 32972.591886205,
    "percentage": 0.048823180767806645,
    "double_amount_for_100_apy": 65945.18377241,
    "sol_equivalent_for_100_apy": 0.08956022052790058,
    "daily_sol_for_100_apy": 0.0002453704671997276
  },
  {
    "owner": "Hg46gQuCegrmUJyXXX29nmHyNJEnMid95CbhCzGjeGRs",
    "amount": 533406.61178657,
    "percentage": 0.7898259111651644,
    "double_amount_for_100_apy": 1066813.22357314,
    "sol_equivalent_for_100_apy": 1.4488401138592994,
    "daily_sol_for_100_apy": 0.003969424969477533
  },
  {
    "owner": "GLkp8nGJQunvEqPkkQodw8EQAVwQJNBuUUmGi7VKm9ye",
    "amount": 85820.543845206,
    "percentage": 0.12707620742120018,
    "double_amount_for_100_apy": 171641.087690412,
    "sol_equivalent_for_100_apy": 0.23310593413848993,
    "daily_sol_for_100_apy": 0.0006386463948999724
  },
  {
    "owner": "4KBB2gLNU5563WvSJ3zWUSB6EkeqFcZD22414Ae8bsow",
    "amount": 93137.099323486,
    "percentage": 0.13790997844977382,
    "double_amount_for_100_apy": 186274.198646972,
    "sol_equivalent_for_100_apy": 0.2529791768729662,
    "daily_sol_for_100_apy": 0.0006930936352684006
  },
  {
    "owner": "CQ5Av6vkg67ytBCK2xYS2wFJStUppcpW2jHC7Y1i7pdm",
    "amount": 165360.000000001,
    "percentage": 0.24485188181831366,
    "double_amount_for_100_apy": 330720.000000002,
    "sol_equivalent_for_100_apy": 0.449151165234595,
    "daily_sol_for_100_apy": 0.0012305511376290274
  },
  {
    "owner": "9mBrTn9kvqSySrpLk29HhvtdYMSxoDz5v1RDjMVUYky4",
    "amount": 89287.606391332,
    "percentage": 0.13220995674873245,
    "double_amount_for_100_apy": 178575.212782664,
    "sol_equivalent_for_100_apy": 0.2425231764131253,
    "daily_sol_for_100_apy": 0.0006644470586660967
  },
  {
    "owner": "HaiL2iBjnCVEAnE5aaQQQPFiEkGUiXELUqKvp4ZFB5VH",
    "amount": 85741.6269652,
    "percentage": 0.12695935360784324,
    "double_amount_for_100_apy": 171483.2539304,
    "sol_equivalent_for_100_apy": 0.2328915799499838,
    "daily_sol_for_100_apy": 0.0006380591231506406
  },
  {
    "owner": "8ixEiWWNpum38cEVtxPbMdkhjwd6FyFiHVDBR5htFpok",
    "amount": 86150.644654724,
    "percentage": 0.1275649943370216,
    "double_amount_for_100_apy": 172301.289309448,
    "sol_equivalent_for_100_apy": 0.23400255462252412,
    "daily_sol_for_100_apy": 0.0006411028893767784
  },
  {
    "owner": "EaGj7kx632FuRU26mtb6UjUvQjLTsnHHME8Yf5dAyg7e",
    "amount": 1219563.287278597,
    "percentage": 1.8058319175537698,
    "double_amount_for_100_apy": 2439126.574557194,
    "sol_equivalent_for_100_apy": 3.312580258578324,
    "daily_sol_for_100_apy": 0.009075562352269381
  },
  {
    "owner": "EpAa65hRE3X19e4mf82vA8rsfaZctAZTiaNFiyWbGfwc",
    "amount": 447419.040543038,
    "percentage": 0.6625023829118685,
    "double_amount_for_100_apy": 894838.081086076,
    "sol_equivalent_for_100_apy": 1.2152804995648816,
    "daily_sol_for_100_apy": 0.003329535615246251
  },
  {
    "owner": "HLnpSz9h2S4hiLQ43rnSD9XkcUThA7B8hQMKmDaiTLcC",
    "amount": 35233.1012334,
    "percentage": 0.05217036247758276,
    "double_amount_for_100_apy": 70466.2024668,
    "sol_equivalent_for_100_apy": 0.09570022057214538,
    "daily_sol_for_100_apy": 0.0002621923851291654
  },
  {
    "owner": "5LmkWykmDykfjZEQwCiTNUzhJwMaNx9Zqtw5k7MYi3KG",
    "amount": 250710.879592311,
    "percentage": 0.3712326479227239,
    "double_amount_for_100_apy": 501421.759184622,
    "sol_equivalent_for_100_apy": 0.6809813963828982,
    "daily_sol_for_100_apy": 0.0018657024558435568
  },
  {
    "owner": "AeJdTTxEVQPfyMuQmt5gbYbp26K6NPXG4Ha4Ybtop31L",
    "amount": 87055.943980993,
    "percentage": 0.1289054892792435,
    "double_amount_for_100_apy": 174111.887961986,
    "sol_equivalent_for_100_apy": 0.2364615304769013,
    "daily_sol_for_100_apy": 0.000647839809525757
  },
  {
    "owner": "HcoXimDTvHHwMCVYL9zruyjGaPsHsxHtbK2weFi1iaUQ",
    "amount": 445390.114565642,
    "percentage": 0.6594981113610976,
    "double_amount_for_100_apy": 890780.229131284,
    "sol_equivalent_for_100_apy": 1.2097695267363733,
    "daily_sol_for_100_apy": 0.0033144370595517077
  },
  {
    "owner": "HFXKmrzmGt8UgYbYBisUEzpcNAETseCqAi5mQjHwNHQC",
    "amount": 86157.058053644,
    "percentage": 0.12757449078594765,
    "double_amount_for_100_apy": 172314.116107288,
    "sol_equivalent_for_100_apy": 0.2340199747095949,
    "daily_sol_for_100_apy": 0.0006411506156427258
  },
  {
    "owner": "3JeCh7isYjwsdRP5Vy4Cmn1fpHzuU2gcRoRPzWc7S4mc",
    "amount": 59653.297571959,
    "percentage": 0.08832983894026315,
    "double_amount_for_100_apy": 119306.595143918,
    "sol_equivalent_for_100_apy": 0.16203040707868446,
    "daily_sol_for_100_apy": 0.0004439189235032451
  },
  {
    "owner": "3vCsgkAmHEipvdpW45AVyDG2s1erWhuftma1J7wMRmf2",
    "amount": 87002.570536074,
    "percentage": 0.1288264581445825,
    "double_amount_for_100_apy": 174005.141072148,
    "sol_equivalent_for_100_apy": 0.23631655741825378,
    "daily_sol_for_100_apy": 0.0006474426230637089
  },
  {
    "owner": "D4j6HS8x8zXEwGpsuMcHaQEmKNbK98h4fy2ZGxzCu2ZJ",
    "amount": 359288.847628522,
    "percentage": 0.5320062316048406,
    "double_amount_for_100_apy": 718577.695257044,
    "sol_equivalent_for_100_apy": 0.9759010919699114,
    "daily_sol_for_100_apy": 0.0026737016218353737
  },
  {
    "owner": "D4Z4mHc7Z4F4RB1mJy2cAgd339mE5FBM7dtVQPzYWyrp",
    "amount": 54303.450933992,
    "percentage": 0.08040821329472861,
    "double_amount_for_100_apy": 108606.901867984,
    "sol_equivalent_for_100_apy": 0.1474991428595913,
    "daily_sol_for_100_apy": 0.000404107240711209
  },
  {
    "owner": "FQ8VCuaXLFgV5Vcs4mPjVJMoZrVisDCSv2zonWFdWqPa",
    "amount": 28269.207612202,
    "percentage": 0.04185878496226546,
    "double_amount_for_100_apy": 56538.415224404,
    "sol_equivalent_for_100_apy": 0.07678487868456177,
    "daily_sol_for_100_apy": 0.000210369530642635
  },
  {
    "owner": "7f2gGGX9Exc7mfNSbxEoyt2ScSaa17kYLD73kva1jyUu",
    "amount": 229878.654680179,
    "percentage": 0.3403859530013533,
    "double_amount_for_100_apy": 459757.309360358,
    "sol_equivalent_for_100_apy": 0.6243968650953245,
    "daily_sol_for_100_apy": 0.0017106763427269167
  },
  {
    "owner": "CGVLSjU6ervN8a8NzQQPNM84zh3LJkg2iXh61wy6HfLC",
    "amount": 84227.649801782,
    "percentage": 0.12471757713534175,
    "double_amount_for_100_apy": 168455.299603564,
    "sol_equivalent_for_100_apy": 0.22877931212773078,
    "daily_sol_for_100_apy": 0.0006267926359663857
  },
  {
    "owner": "7xF7qq5uRE36oTecfMQqjt5mqLKXXcGZZJrPgwuihw5k",
    "amount": 64900.207063367,
    "percentage": 0.09609904348006487,
    "double_amount_for_100_apy": 129800.414126734,
    "sol_equivalent_for_100_apy": 0.1762820732128544,
    "daily_sol_for_100_apy": 0.0004829645841448066
  },
  {
    "owner": "8D16nTyDWoaKR9zwhohY97wacTj8DmDsWarGUrQgkt5D",
    "amount": 46799.335632803,
    "percentage": 0.06929671865952229,
    "double_amount_for_100_apy": 93598.671265606,
    "sol_equivalent_for_100_apy": 0.12711644975615774,
    "daily_sol_for_100_apy": 0.0003482642459072815
  },
  {
    "owner": "GYfALc5YvW5tC6fokRoyiGL4jSCJDWn5aVk4QUE2Hc5m",
    "amount": 54606.453148263,
    "percentage": 0.08085687477488929,
    "double_amount_for_100_apy": 109212.906296526,
    "sol_equivalent_for_100_apy": 0.14832215808460628,
    "daily_sol_for_100_apy": 0.0004063620769441268
  },
  {
    "owner": "6CfkBeNfhQBsie4xsoksgQmqWyx5Y5iA3crzEoNMGp8A",
    "amount": 101053.822144589,
    "percentage": 0.14963242934830456,
    "double_amount_for_100_apy": 202107.644289178,
    "sol_equivalent_for_100_apy": 0.27448259535347963,
    "daily_sol_for_100_apy": 0.0007520071105574784
  },
  {
    "owner": "8Veq3G65cAv88foMN4yWNwd8z1visrpkCpmhuu9iaSJP",
    "amount": 85669.273971282,
    "percentage": 0.1268522190727924,
    "double_amount_for_100_apy": 171338.547942564,
    "sol_equivalent_for_100_apy": 0.2326950546020975,
    "daily_sol_for_100_apy": 0.0006375206975399931
  }
]