[
  {
    "owner": "9RBAYbLc4LkXwW4q3QJPVZTT23x5cRt7FUFPgwAiEoAe",
    "amount": 79299.180180809,
    "percentage": 0.12624120922137116,
    "double_amount_for_100_apy": 158598.360361618,
    "sol_equivalent_for_100_apy": 0.21539259301135855,
    "daily_sol_for_100_apy": 0.0005901166931818043
  },
  {
    "owner": "2BZe9ksdrKAdcqZb3vPbD2iuAuasnv84McbGPPrXrwyL",
    "amount": 2062087.69040589,
    "percentage": 3.2827633648139973,
    "double_amount_for_100_apy": 4124175.38081178,
    "sol_equivalent_for_100_apy": 5.601046740213563,
    "daily_sol_for_100_apy": 0.015345333534831678
  },
  {
    "owner": "H5iSDfqA1hj3GykihjWkLHMZdzCmCJrhLDW2cvV6d1JV",
    "amount": 40529.340641635,
    "percentage": 0.06452113325609247,
    "double_amount_for_100_apy": 81058.68128327,
    "sol_equivalent_for_100_apy": 0.11008587672581083,
    "daily_sol_for_100_apy": 0.00030160514171455023
  },
  {
    "owner": "6CfkBeNfhQBsie4xsoksgQmqWyx5Y5iA3crzEoNMGp8A",
    "amount": 100549.822144589,
    "percentage": 0.1600714043396712,
    "double_amount_for_100_apy": 201099.644289178,
    "sol_equivalent_for_100_apy": 0.2731136295378154,
    "daily_sol_for_100_apy": 0.0007482565192816861
  },
  {
    "owner": "FRTT1miwwfTHch5sVFSoV9EY8fgcN1s8aq6ZgBWWBmWr",
    "amount": 105518.63081828,
    "percentage": 0.16798155440586562,
    "double_amount_for_100_apy": 211037.26163656,
    "sol_equivalent_for_100_apy": 0.28660991767047184,
    "daily_sol_for_100_apy": 0.0007852326511519777
  },
  {
    "owner": "2YG3BRuKEBGQgiG32ZRcZm8u7g8zKzKU82ZxwQqx2Cpo",
    "amount": 88135.95140779,
    "percentage": 0.14030900516532818,
    "double_amount_for_100_apy": 176271.90281558,
    "sol_equivalent_for_100_apy": 0.23939504882600557,
    "daily_sol_for_100_apy": 0.0006558768460986454
  },
  {
    "owner": "3AM6w3nzniZNt196FsDh7JKLXsEmAzCi8oL9agJaR9f4",
    "amount": 84488.958670141,
    "percentage": 0.13450313463586477,
    "double_amount_for_100_apy": 168977.917340282,
    "sol_equivalent_for_100_apy": 0.2294890798025589,
    "daily_sol_for_100_apy": 0.0006287372049385175
  },
  {
    "owner": "B3bBT3W4r8MfvcanKw7QQ17GYrXKT6qXRbmkjrojbyCy",
    "amount": 33012.489534776,
    "percentage": 0.05255459878369031,
    "double_amount_for_100_apy": 66024.979069552,
    "sol_equivalent_for_100_apy": 0.08966859060135114,
    "daily_sol_for_100_apy": 0.0002456673715105511
  },
  {
    "owner": "3n3pCV1pkWvjzhXYDM9TM95rzBa8RBQmz1LJGauHrVbT",
    "amount": 822059.139232208,
    "percentage": 1.308686162347848,
    "double_amount_for_100_apy": 1644118.278464416,
    "sol_equivalent_for_100_apy": 2.23287869060167,
    "daily_sol_for_100_apy": 0.00611747586466211
  },
  {
    "owner": "GhCfaPPdUjho2gLL2FCBAVbGtXxYWP97MgdYcXV8AbQt",
    "amount": 587489.434690664,
    "percentage": 0.9352603201070391,
    "double_amount_for_100_apy": 1174978.869381328,
    "sol_equivalent_for_100_apy": 1.5957399864194706,
    "daily_sol_for_100_apy": 0.0043718903737519745
  },
  {
    "owner": "AEy1bDga7DXu5rXGemtXch9ZBw6hXeJhjzhm5ymNjgtV",
    "amount": 85108.170287745,
    "percentage": 0.13548889543682155,
    "double_amount_for_100_apy": 170216.34057549,
    "sol_equivalent_for_100_apy": 0.23117098364613434,
    "daily_sol_for_100_apy": 0.0006333451606743407
  },
  {
    "owner": "8ccAjDpyEv5CiEBV8YUJYVzMQ9NGWdNR7sYWSPPa3Air",
    "amount": 93757.98253752,
    "percentage": 0.14925905996386526,
    "double_amount_for_100_apy": 187515.96507504,
    "sol_equivalent_for_100_apy": 0.2546656211101334,
    "daily_sol_for_100_apy": 0.0006977140304387216
  },
  {
    "owner": "ButcZhoUCaY8gbKRGcPkdgxTJS3tHpqUAMdaE5kGYzbF",
    "amount": 87718.973462409,
    "percentage": 0.139645192501395,
    "double_amount_for_100_apy": 175437.946924818,
    "sol_equivalent_for_100_apy": 0.23826245249046493,
    "daily_sol_for_100_apy": 0.0006527738424396299
  },
  {
    "owner": "5gpRqRf375S1Rsz575cAbfnM9cT5dkC2EB5kjSodHxwL",
    "amount": 594899.327999999,
    "percentage": 0.9470565819276395,
    "double_amount_for_100_apy": 1189798.655999998,
    "sol_equivalent_for_100_apy": 1.6158667535587536,
    "daily_sol_for_100_apy": 0.004427032201530832
  },
  {
    "owner": "3HhWTLVug55hpRWU6FsxDGCHDKBmmYSXaySUbMoDoYqD",
    "amount": 84358.253630968,
    "percentage": 0.13429505729939162,
    "double_amount_for_100_apy": 168716.507261936,
    "sol_equivalent_for_100_apy": 0.22913405851175953,
    "daily_sol_for_100_apy": 0.0006277645438678343
  },
  {
    "owner": "D4Z4mHc7Z4F4RB1mJy2cAgd339mE5FBM7dtVQPzYWyrp",
    "amount": 54030.450933992,
    "percentage": 0.08601437549708509,
    "double_amount_for_100_apy": 108060.901867984,
    "sol_equivalent_for_100_apy": 0.14675761970943985,
    "daily_sol_for_100_apy": 0.0004020756704368215
  },
  {
    "owner": "8NtZ91dXwb1RpRK6kLpb29xPkscCvjgrsWYZJJQGPFuw",
    "amount": 91618.64804636,
    "percentage": 0.14585332269801665,
    "double_amount_for_100_apy": 183237.29609272,
    "sol_equivalent_for_100_apy": 0.24885475645404329,
    "daily_sol_for_100_apy": 0.0006817938532987487
  },
  {
    "owner": "JDTybisdWYmqxsGAmX9Y4PgaFkN9oP5qrH1nsKfMQJta",
    "amount": 285200.579,
    "percentage": 0.45402822427045036,
    "double_amount_for_100_apy": 570401.158,
    "sol_equivalent_for_100_apy": 0.774662387417939,
    "daily_sol_for_100_apy": 0.0021223627052546273
  },
  {
    "owner": "53cQzmcVtg55SUEHAtTC87emqZKfdAPGbz86PirMdcLZ",
    "amount": 47126.425229522,
    "percentage": 0.07502343521951273,
    "double_amount_for_100_apy": 94252.850459044,
    "sol_equivalent_for_100_apy": 0.12800489117791905,
    "daily_sol_for_100_apy": 0.0003506983319942988
  },
  {
    "owner": "A2S5cnnwcf8p6MQz7Y3WQc5Eok1fr8RLSBYd6YY1jmbj",
    "amount": 75839.85864454,
    "percentage": 0.12073410394199255,
    "double_amount_for_100_apy": 151679.71728908,
    "sol_equivalent_for_100_apy": 0.2059963768832965,
    "daily_sol_for_100_apy": 0.0005643736352967028
  },
  {
    "owner": "DXhK4NoqyG2NCh135JFQKaecq7wKebiJzRnCsES7jjth",
    "amount": 82688.357064645,
    "percentage": 0.13163664694348925,
    "double_amount_for_100_apy": 165376.71412929,
    "sol_equivalent_for_100_apy": 0.2245982820931261,
    "daily_sol_for_100_apy": 0.0006153377591592495
  },
  {
    "owner": "9Gxdt1xEUutWEMsckvKxsR4iqJ53fnMLfE5RHLjyjrH2",
    "amount": 82876.087064345,
    "percentage": 0.1319355057982116,
    "double_amount_for_100_apy": 165752.17412869,
    "sol_equivalent_for_100_apy": 0.22510819469662602,
    "daily_sol_for_100_apy": 0.0006167347799907562
  },
  {
    "owner": "98n96p8o8RZVP22BFoMScaS3VXGMgQ5zGj7Dbvy9cGji",
    "amount": 47859.61209021,
    "percentage": 0.07619064017254544,
    "double_amount_for_100_apy": 95719.22418042,
    "sol_equivalent_for_100_apy": 0.12999637480644294,
    "daily_sol_for_100_apy": 0.0003561544515245012
  },
  {
    "owner": "AyvWC5qage5GVdUCregpEX67nRiJV9CVb3nrAMSP9aqR",
    "amount": 120123.603477181,
    "percentage": 0.19123210258178394,
    "double_amount_for_100_apy": 240247.206954362,
    "sol_equivalent_for_100_apy": 0.32627997383861856,
    "daily_sol_for_100_apy": 0.0008939177365441604
  },
  {
    "owner": "2s2As1LnQ8PUtcTviaEXRfa5DQT9oYmAzy3CR6B9aVhu",
    "amount": 1189510.328999999,
    "percentage": 1.893654158490431,
    "double_amount_for_100_apy": 2379020.657999998,
    "sol_equivalent_for_100_apy": 3.230950352739071,
    "daily_sol_for_100_apy": 0.008851918774627592
  },
  {
    "owner": "82sxBeYejDgAeLFATgTkR9cRMS5Hdm3jFVGZ5MbCnAXB",
    "amount": 88357.697410245,
    "percentage": 0.1406620161728329,
    "double_amount_for_100_apy": 176715.39482049,
    "sol_equivalent_for_100_apy": 0.2399973557647379,
    "daily_sol_for_100_apy": 0.0006575270020951723
  },
  {
    "owner": "GK2RYjoxaEWU6Fw9wj4p9MZ8nE34xLPWowvpBY2LpzwG",
    "amount": 288368.127735506,
    "percentage": 0.4590708386042448,
    "double_amount_for_100_apy": 576736.255471012,
    "sol_equivalent_for_100_apy": 0.7832660896765861,
    "daily_sol_for_100_apy": 0.002145934492264619
  },
  {
    "owner": "7WRiimDiPyFvCmVnsdDSg5L9xEXhJxvVYaPCrJxehPAH",
    "amount": 1230388.165233267,
    "percentage": 1.9587300831680206,
    "double_amount_for_100_apy": 2460776.330466534,
    "sol_equivalent_for_100_apy": 3.341982813893166,
    "daily_sol_for_100_apy": 0.009156117298337442
  },
  {
    "owner": "GME8jEUdr1xu2hBBU4pJLQRQHRBYW2kHwnH2YVGLHatF",
    "amount": 845579.157830775,
    "percentage": 1.3461291167645546,
    "double_amount_for_100_apy": 1691158.31566155,
    "sol_equivalent_for_100_apy": 2.2967638125167986,
    "daily_sol_for_100_apy": 0.006292503595936434
  },
  {
    "owner": "S1n39sNU9YSwwviMVjgYk5ZLdyqoojDnFPvbxGxixqB",
    "amount": 85743.454143317,
    "percentage": 0.13650024261523325,
    "double_amount_for_100_apy": 171486.908286634,
    "sol_equivalent_for_100_apy": 0.2328965429348673,
    "daily_sol_for_100_apy": 0.0006380727203694995
  },
  {
    "owner": "9y9HNKiqfRaUU3WHAooWfCvA15U7f8acS7LNZvcE8fvr",
    "amount": 80919.203756665,
    "percentage": 0.1288202237170681,
    "double_amount_for_100_apy": 161838.40751333,
    "sol_equivalent_for_100_apy": 0.2197929043127811,
    "daily_sol_for_100_apy": 0.0006021723405829619
  },
  {
    "owner": "9mBrTn9kvqSySrpLk29HhvtdYMSxoDz5v1RDjMVUYky4",
    "amount": 87943.801676027,
    "percentage": 0.14000311026913864,
    "double_amount_for_100_apy": 175887.603352054,
    "sol_equivalent_for_100_apy": 0.23887313133736948,
    "daily_sol_for_100_apy": 0.0006544469351708752
  },
  {
    "owner": "GNXVuVWJk3TgEpBdMaphhGnJQGj3RE2dhX1SdoQzQHAM",
    "amount": 89381.404643623,
    "percentage": 0.14229171825469095,
    "double_amount_for_100_apy": 178762.809287246,
    "sol_equivalent_for_100_apy": 0.24277795141502098,
    "daily_sol_for_100_apy": 0.0006651450723699205
  },
  {
    "owner": "627L8LHowp7qzshnQJSgpoenCpJfYpyHprf5UjQsu9FT",
    "amount": 85779.293355768,
    "percentage": 0.13655729724690838,
    "double_amount_for_100_apy": 171558.586711536,
    "sol_equivalent_for_100_apy": 0.23299388947595015,
    "daily_sol_for_100_apy": 0.0006383394232217812
  },
  {
    "owner": "3fM5cdu7uDHkqGEDTBzJs3gECu6wyBNTXKpFYZwZ1TZ8",
    "amount": 1139344.999999999,
    "percentage": 1.813792906715718,
    "double_amount_for_100_apy": 2278689.999999998,
    "sol_equivalent_for_100_apy": 3.0946911850157606,
    "daily_sol_for_100_apy": 0.00847860598634455
  },
  {
    "owner": "7ftDeYapdZ9xHQ2X8XX14x5gSdcacPeeBi23xDAozMct",
    "amount": 84657.191912335,
    "percentage": 0.1347709554112798,
    "double_amount_for_100_apy": 169314.38382467,
    "sol_equivalent_for_100_apy": 0.22994603527403099,
    "daily_sol_for_100_apy": 0.0006299891377370712
  },
  {
    "owner": "4v91uQbk67t28xULRseArTsHJ8aMeSx5UUNpzuD5GQRe",
    "amount": 81660.61685267,
    "percentage": 0.1300005245166328,
    "double_amount_for_100_apy": 163321.23370534,
    "sol_equivalent_for_100_apy": 0.22180673205825058,
    "daily_sol_for_100_apy": 0.0006076896768719194
  },
  {
    "owner": "7xF7qq5uRE36oTecfMQqjt5mqLKXXcGZZJrPgwuihw5k",
    "amount": 64583.207063367,
    "percentage": 0.10281395263461693,
    "double_amount_for_100_apy": 129166.414126734,
    "sol_equivalent_for_100_apy": 0.17542103717403387,
    "daily_sol_for_100_apy": 0.0004806055812987229
  },
  {
    "owner": "5mxsR8Bt4DqsYxVkkdyaurXAJ9T94xnXTjbtPPmJ74bq",
    "amount": 47693.487018857,
    "percentage": 0.0759261755230778,
    "double_amount_for_100_apy": 95386.974037714,
    "sol_equivalent_for_100_apy": 0.12954514555285754,
    "daily_sol_for_100_apy": 0.00035491820699413024
  },
  {
    "owner": "AJwVgVuETmuu8uRw5Fi4LeJYZTynHR8VTcvBHhgkN5Kr",
    "amount": 796084.638325784,
    "percentage": 1.2673357676038917,
    "double_amount_for_100_apy": 1592169.276651568,
    "sol_equivalent_for_100_apy": 2.162326698895651,
    "daily_sol_for_100_apy": 0.005924182736700413
  },
  {
    "owner": "4tCukTai7QuXKkFbFHoiQDGnmETKEAbU2m8mutzD9NLZ",
    "amount": 171560.062850298,
    "percentage": 0.2731169444492876,
    "double_amount_for_100_apy": 343120.125700596,
    "sol_equivalent_for_100_apy": 0.4659917884429804,
    "daily_sol_for_100_apy": 0.0012766898313506313
  },
  {
    "owner": "9GReid1CpJaJuEto7jarjLDeGWASYDDAwZxBeWEbnKq1",
    "amount": 1218175.733450482,
    "percentage": 1.9392883669702357,
    "double_amount_for_100_apy": 2436351.466900964,
    "sol_equivalent_for_100_apy": 3.30881138207419,
    "daily_sol_for_100_apy": 0.00906523666321696
  },
  {
    "owner": "4RXTm8McowoyoQ5F2VvsgY9kJMqFhbany8XTiPFQ2Pdw",
    "amount": 164994.286065357,
    "percentage": 0.26266448328993314,
    "double_amount_for_100_apy": 329988.572130714,
    "sol_equivalent_for_100_apy": 0.4481578123083258,
    "daily_sol_for_100_apy": 0.0012278296227625364
  },
  {
    "owner": "DKoTRmcy93NBbK67UgqdyUf8hSMAkP5TToj5mvm612K",
    "amount": 234940.777037078,
    "percentage": 0.37401657521482207,
    "double_amount_for_100_apy": 469881.554074156,
    "sol_equivalent_for_100_apy": 0.6381466120423568,
    "daily_sol_for_100_apy": 0.0017483468823078269
  },
  {
    "owner": "EY9ksz8A7wPaHLipbdvyRNoBUGeMUbiEKoXdVd3GL6iX",
    "amount": 590755.212317861,
    "percentage": 0.9404593110142013,
    "double_amount_for_100_apy": 1181510.424635722,
    "sol_equivalent_for_100_apy": 1.6046104981916802,
    "daily_sol_for_100_apy": 0.00439619314573063
  },
  {
    "owner": "MXTEi69QBHmupFUjGNNyW5sc336ErrksbRHrhG4ypo1",
    "amount": 70720.535035995,
    "percentage": 0.1125843399562277,
    "double_amount_for_100_apy": 141441.07007199,
    "sol_equivalent_for_100_apy": 0.19209125978127092,
    "daily_sol_for_100_apy": 0.0005262774240582765
  },
  {
    "owner": "4EG5qw8sKMURwTJ3s7w5Z6Un3VTtPiJ8DYKKobjxMAGw",
    "amount": 84358.803344978,
    "percentage": 0.13429593242270552,
    "double_amount_for_100_apy": 168717.606689956,
    "sol_equivalent_for_100_apy": 0.22913555164606128,
    "daily_sol_for_100_apy": 0.0006277686346467433
  },
  {
    "owner": "4aYHhiJYGibcN28cpVL24SNRCRtsHrexwKiU1pynM5pc",
    "amount": 425159.402364457,
    "percentage": 0.6768372251005154,
    "double_amount_for_100_apy": 850318.804728914,
    "sol_equivalent_for_100_apy": 1.1548188254864462,
    "daily_sol_for_100_apy": 0.0031638871931135514
  },
  {
    "owner": "DCM312seeKsTPWGiZsxoPKX6KnnNVmZvdVMnbiup7AT2",
    "amount": 56438.035921556,
    "percentage": 0.08984715711525942,
    "double_amount_for_100_apy": 112876.071843112,
    "sol_equivalent_for_100_apy": 0.15329710690444276,
    "daily_sol_for_100_apy": 0.00041999207371080206
  },
  {
    "owner": "DJoiju2i7qqJTi8fuUPYyycjE5zE99mPZwsHeKZ8z2fm",
    "amount": 43618.528403956,
    "percentage": 0.0694389999696962,
    "double_amount_for_100_apy": 87237.056807912,
    "sol_equivalent_for_100_apy": 0.11847673475117923,
    "daily_sol_for_100_apy": 0.0003245937938388472
  },
  {
    "owner": "8otm8ek2xjXDodyE3c2nXzVdhHQFm2srQF6D7nvnjNLH",
    "amount": 111455.574383411,
    "percentage": 0.1774329375479395,
    "double_amount_for_100_apy": 222911.148766822,
    "sol_equivalent_for_100_apy": 0.30273585574624956,
    "daily_sol_for_100_apy": 0.0008294133034143824
  },
  {
    "owner": "2S2e3rJwhjUEJqinGwV6RmGhVAKJXXkNpFsmhKmpcPH1",
    "amount": 77253.261275413,
    "percentage": 0.12298418593314603,
    "double_amount_for_100_apy": 154506.522550826,
    "sol_equivalent_for_100_apy": 0.20983546395757227,
    "daily_sol_for_100_apy": 0.0005748916820755405
  },
  {
    "owner": "76QmSGCVUzk7YXmFWVCpaRKWVF1dW4PXTeVxiKnkJzDC",
    "amount": 46966.791561603,
    "percentage": 0.0747693046317237,
    "double_amount_for_100_apy": 93933.583123206,
    "sol_equivalent_for_100_apy": 0.1275712938874226,
    "daily_sol_for_100_apy": 0.00034951039421211676
  },
  {
    "owner": "9J7zDLKnaRWK9LtZuyGzikJAVzABj1kcn5eMNp5Xmiah",
    "amount": 221703.217422955,
    "percentage": 0.35294289539850415,
    "double_amount_for_100_apy": 443406.43484591,
    "sol_equivalent_for_100_apy": 0.6021907259420561,
    "daily_sol_for_100_apy": 0.0016498376053207017
  },
  {
    "owner": "8gQjeMVhKVj3RbjEQHvxFADNTXhq9QbMVvAYPe9uZSSy",
    "amount": 84636.109369234,
    "percentage": 0.13473739282301014,
    "double_amount_for_100_apy": 169272.218738468,
    "sol_equivalent_for_100_apy": 0.22988877082797438,
    "daily_sol_for_100_apy": 0.0006298322488437655
  },
  {
    "owner": "36to2vW2mmkovE9MVNyZ24CEueEW5TFgcS269DPMjfvD",
    "amount": 88302.278746225,
    "percentage": 0.14057379181611993,
    "double_amount_for_100_apy": 176604.55749245,
    "sol_equivalent_for_100_apy": 0.2398468274778467,
    "daily_sol_for_100_apy": 0.0006571145958297169
  },
  {
    "owner": "Df9TCSZfVdaYAqvpNgbVHQcBiXvamRTWzA8BoJkAuvtA",
    "amount": 891871.999999999,
    "percentage": 1.4198255201877923,
    "double_amount_for_100_apy": 1783743.999999998,
    "sol_equivalent_for_100_apy": 2.4225045237064937,
    "daily_sol_for_100_apy": 0.006636998695086284
  },
  {
    "owner": "B4hhtcJS2H6Kkn9iK87Q6ZjSK4hECXq17zGJqBxDnzeq",
    "amount": 240325.070164203,
    "percentage": 0.38258816036388366,
    "double_amount_for_100_apy": 480650.140328406,
    "sol_equivalent_for_100_apy": 0.6527714398847178,
    "daily_sol_for_100_apy": 0.0017884149037937472
  },
  {
    "owner": "HdbfQg4wsYaM6J7jeP84CCvzqrsjgXJHoMerbhjdJxwt",
    "amount": 82794.083223261,
    "percentage": 0.13180495887407392,
    "double_amount_for_100_apy": 165588.166446522,
    "sol_equivalent_for_100_apy": 0.22488545569821894,
    "daily_sol_for_100_apy": 0.000616124536159504
  },
  {
    "owner": "3cQNE1dT2ea8rXMokAWfrQposyQjEGjUdCGaTfCcmK2j",
    "amount": 347107.949973854,
    "percentage": 0.5525823499705631,
    "double_amount_for_100_apy": 694215.899947708,
    "sol_equivalent_for_100_apy": 0.9428153132132746,
    "daily_sol_for_100_apy": 0.0025830556526391085
  },
  {
    "owner": "6ncLPo29tzHkzDwsMZcqa1qH4yWvGTWZfC7Uv7iiNMov",
    "amount": 84998.201075109,
    "percentage": 0.13531382872933936,
    "double_amount_for_100_apy": 169996.402150218,
    "sol_equivalent_for_100_apy": 0.2308722850491617,
    "daily_sol_for_100_apy": 0.0006325268083538677
  },
  {
    "owner": "ZY7KnsopGG7TwkU8Km5QkhyU6Xwn46qGuWU6HV3wUQc",
    "amount": 83310.228013295,
    "percentage": 0.1326266412959935,
    "double_amount_for_100_apy": 166620.45602659,
    "sol_equivalent_for_100_apy": 0.22628740921704776,
    "daily_sol_for_100_apy": 0.0006199655047042404
  },
  {
    "owner": "4KBB2gLNU5563WvSJ3zWUSB6EkeqFcZD22414Ae8bsow",
    "amount": 91797.467724539,
    "percentage": 0.14613799666758887,
    "double_amount_for_100_apy": 183594.935449078,
    "sol_equivalent_for_100_apy": 0.24934046682427172,
    "daily_sol_for_100_apy": 0.0006831245666418403
  },
  {
    "owner": "BRRr9HZxnBABesPepcTQXMXuWCt5aFEMUuhrJ4y8uEEL",
    "amount": 255925.803962953,
    "percentage": 0.40742392152817797,
    "double_amount_for_100_apy": 511851.607925906,
    "sol_equivalent_for_100_apy": 0.695146184467587,
    "daily_sol_for_100_apy": 0.0019045100944317453
  },
  {
    "owner": "CGVLSjU6ervN8a8NzQQPNM84zh3LJkg2iXh61wy6HfLC",
    "amount": 82934.338197758,
    "percentage": 0.1320282393359834,
    "double_amount_for_100_apy": 165868.676395516,
    "sol_equivalent_for_100_apy": 0.22526641654259047,
    "daily_sol_for_100_apy": 0.0006171682645002478
  },
  {
    "owner": "D7qLRacXg2H2Hg5xMjaqygfWdgeYrXf4TUmQcCf5T99s",
    "amount": 1038170.599566623,
    "percentage": 1.65272719804339,
    "double_amount_for_100_apy": 2076341.199133246,
    "sol_equivalent_for_100_apy": 2.819881074671287,
    "daily_sol_for_100_apy": 0.007725701574441882
  },
  {
    "owner": "D2MQVUmGPum9Joc53A9FNDFXBSGCCP38bpGXFUh5e62n",
    "amount": 106247.85609458,
    "percentage": 0.16914245267070266,
    "double_amount_for_100_apy": 212495.71218916,
    "sol_equivalent_for_100_apy": 0.2885906408354976,
    "daily_sol_for_100_apy": 0.0007906592899602675
  },
  {
    "owner": "47MD734cLCRpwic4wcYTTtXmrUy6Z1xUpP7CFH6PjcSt",
    "amount": 83362.626674204,
    "percentage": 0.1327100579252657,
    "double_amount_for_100_apy": 166725.253348408,
    "sol_equivalent_for_100_apy": 0.22642973456540297,
    "daily_sol_for_100_apy": 0.0006203554371654876
  },
  {
    "owner": "6vPLQSv1zBoMxw5tWddu7uoq22swzBiJqLVXvMfTnm1z",
    "amount": 266607.2040243,
    "percentage": 0.42442829479971905,
    "double_amount_for_100_apy": 533214.4080486,
    "sol_equivalent_for_100_apy": 0.7241590248394474,
    "daily_sol_for_100_apy": 0.001983997328327253
  },
  {
    "owner": "3t35yLb3PmKYVwEULLnQSgpwGrr9P2K5MbSGVj6LzDvt",
    "amount": 84404.776412233,
    "percentage": 0.13436911975690813,
    "double_amount_for_100_apy": 168809.552824466,
    "sol_equivalent_for_100_apy": 0.22926042378398453,
    "daily_sol_for_100_apy": 0.0006281107500931084
  },
  {
    "owner": "8TnnKg7QkWfa1V8Mp7utZMEAk8XKMqqpC2TSVvxtW5Ht",
    "amount": 69537.73664129,
    "percentage": 0.11070137093596548,
    "double_amount_for_100_apy": 139075.47328258,
    "sol_equivalent_for_100_apy": 0.1888785403979899,
    "daily_sol_for_100_apy": 0.0005174754531451778
  },
  {
    "owner": "FTchTFMP5w6y1ZL2PksHHNjPpprrsDq67MAEpNrKFYSc",
    "amount": 77985.771650173,
    "percentage": 0.12415031394690428,
    "double_amount_for_100_apy": 155971.543300346,
    "sol_equivalent_for_100_apy": 0.2118251101136553,
    "daily_sol_for_100_apy": 0.000580342767434672
  },
  {
    "owner": "HaiL2iBjnCVEAnE5aaQQQPFiEkGUiXELUqKvp4ZFB5VH",
    "amount": 84346.826754342,
    "percentage": 0.13427686615643655,
    "double_amount_for_100_apy": 168693.653508684,
    "sol_equivalent_for_100_apy": 0.22910302080644043,
    "daily_sol_for_100_apy": 0.0006276795090587409
  },
  {
    "owner": "2iMbbqGkfxoYutXnwbBikTSh1AWrZLFcWy2e9mqWaTei",
    "amount": 84259.920083223,
    "percentage": 0.1341385141176582,
    "double_amount_for_100_apy": 168519.840166446,
    "sol_equivalent_for_100_apy": 0.2288669647312121,
    "daily_sol_for_100_apy": 0.0006270327800855126
  },
  {
    "owner": "2ZfSrM6pVYE9LgDMhERr4irgBGEjm3ScnLEz5a6pXrCA",
    "amount": 84445.092566898,
    "percentage": 0.13443330150638477,
    "double_amount_for_100_apy": 168890.185133796,
    "sol_equivalent_for_100_apy": 0.229369930604531,
    "daily_sol_for_100_apy": 0.000628410768779537
  },
  {
    "owner": "9aBMk5SvGaBL1iPiqVoBiBVwttc4ZsJq5AfNhkQ3g8nS",
    "amount": 82856.236605565,
    "percentage": 0.13190390464023904,
    "double_amount_for_100_apy": 165712.47321113,
    "sol_equivalent_for_100_apy": 0.225054276840485,
    "daily_sol_for_100_apy": 0.0006165870598369452
  },
  {
    "owner": "Go4tyRttPra4z5Hx8vMeixBRrHtDs4DevgMuAK12jTDJ",
    "amount": 32647.582740502,
    "percentage": 0.05197368136616835,
    "double_amount_for_100_apy": 65295.165481004,
    "sol_equivalent_for_100_apy": 0.08867743003138145,
    "daily_sol_for_100_apy": 0.0002429518630996752
  },
  {
    "owner": "FAMmEYXoJNnK47n51ZvW1s5CTsWdFTDmCZZY2TdBBLgD",
    "amount": 473033.614463104,
    "percentage": 0.7530511079183886,
    "double_amount_for_100_apy": 946067.228926208,
    "sol_equivalent_for_100_apy": 1.2848548568652276,
    "daily_sol_for_100_apy": 0.0035201502927814455
  },
  {
    "owner": "8b8Lm5n7deoZD9bNNcWqoRmpG1ZzoNfwA6Jbe3bNsBBx",
    "amount": 129667.587843564,
    "percentage": 0.20642575432515514,
    "double_amount_for_100_apy": 259335.175687128,
    "sol_equivalent_for_100_apy": 0.35220336340769004,
    "daily_sol_for_100_apy": 0.0009649407216649042
  },
  {
    "owner": "HXaE7of4dzmG4EnUb33xHfhmtLRBuuaUdixUzGFyiWWP",
    "amount": 84333.124820133,
    "percentage": 0.13425505321033457,
    "double_amount_for_100_apy": 168666.249640266,
    "sol_equivalent_for_100_apy": 0.22906580358512973,
    "daily_sol_for_100_apy": 0.0006275775440688486
  },
  {
    "owner": "7Ekwo8CXReGdMTVxLYVFtNyVrtcwvu13nfdvu3GgYjHu",
    "amount": 84782.295041749,
    "percentage": 0.13497011472539366,
    "double_amount_for_100_apy": 169564.590083498,
    "sol_equivalent_for_100_apy": 0.23028584064625401,
    "daily_sol_for_100_apy": 0.0006309201113596
  },
  {
    "owner": "ANtrL5Bo5bpyWy2ympjK9AgHshjwvf56fWsY2A6W7ZY5",
    "amount": 67861.640058237,
    "percentage": 0.10803309039467905,
    "double_amount_for_100_apy": 135723.280116474,
    "sol_equivalent_for_100_apy": 0.18432592348142013,
    "daily_sol_for_100_apy": 0.0005050025300860825
  },
  {
    "owner": "2uep9rqRhLqnoPa3QJHsx9r97VNzt9vmdWc2YNgo77aj",
    "amount": 36908.181711014,
    "percentage": 0.05875638914219313,
    "double_amount_for_100_apy": 73816.363422028,
    "sol_equivalent_for_100_apy": 0.10025007754107405,
    "daily_sol_for_100_apy": 0.0002746577466878741
  },
  {
    "owner": "BVMZDy2pZAe8u4jWAEpV4H3VDPiNmz594USLHnkyU4Zt",
    "amount": 78130.533019014,
    "percentage": 0.12438076841326015,
    "double_amount_for_100_apy": 156261.066038028,
    "sol_equivalent_for_100_apy": 0.21221831123542528,
    "daily_sol_for_100_apy": 0.0005814200307819871
  },
  {
    "owner": "E3AR3YNiNyi9rSqmt99Fmf8XnXwgEZsADTxz2koaR3fR",
    "amount": 158732.586884024,
    "percentage": 0.2526961018434973,
    "double_amount_for_100_apy": 317465.173768048,
    "sol_equivalent_for_100_apy": 0.4311497723733705,
    "daily_sol_for_100_apy": 0.0011812322530777273
  },
  {
    "owner": "EpAa65hRE3X19e4mf82vA8rsfaZctAZTiaNFiyWbGfwc",
    "amount": 445232.040543038,
    "percentage": 0.7087920840303227,
    "double_amount_for_100_apy": 890464.081086076,
    "sol_equivalent_for_100_apy": 1.2093401657576244,
    "daily_sol_for_100_apy": 0.0033132607281030806
  },
  {
    "owner": "GYfALc5YvW5tC6fokRoyiGL4jSCJDWn5aVk4QUE2Hc5m",
    "amount": 54333.453148263,
    "percentage": 0.08649674323202393,
    "double_amount_for_100_apy": 108666.906296526,
    "sol_equivalent_for_100_apy": 0.14758063493445484,
    "daily_sol_for_100_apy": 0.00040433050666973926
  },
  {
    "owner": "GLkp8nGJQunvEqPkkQodw8EQAVwQJNBuUUmGi7VKm9ye",
    "amount": 84619.496496971,
    "percentage": 0.13471094577679427,
    "double_amount_for_100_apy": 169238.992993942,
    "sol_equivalent_for_100_apy": 0.22984364691085526,
    "daily_sol_for_100_apy": 0.0006297086216735761
  },
  {
    "owner": "Hg46gQuCegrmUJyXXX29nmHyNJEnMid95CbhCzGjeGRs",
    "amount": 530667.61178657,
    "percentage": 0.8448021890491921,
    "double_amount_for_100_apy": 1061335.22357314,
    "sol_equivalent_for_100_apy": 1.441400436539648,
    "daily_sol_for_100_apy": 0.0039490422918894465
  },
  {
    "owner": "H1vNWJp5rTNs61dvWN9p73dFpGanZE5QcPn22ZyjmsL3",
    "amount": 363313.975231586,
    "percentage": 0.5783817115849381,
    "double_amount_for_100_apy": 726627.950463172,
    "sol_equivalent_for_100_apy": 0.9868341516768182,
    "daily_sol_for_100_apy": 0.0027036552100734744
  },
  {
    "owner": "9gTVfK8CZjdP3KfNLaWFMgGA1FkDdeviLXNtcAqBxDnP",
    "amount": 83648.775949159,
    "percentage": 0.1331655964365816,
    "double_amount_for_100_apy": 167297.551898318,
    "sol_equivalent_for_100_apy": 0.22720697380268567,
    "daily_sol_for_100_apy": 0.0006224848597333854
  },
  {
    "owner": "EaGj7kx632FuRU26mtb6UjUvQjLTsnHHME8Yf5dAyg7e",
    "amount": 1189175.999999999,
    "percentage": 1.8931219197315747,
    "double_amount_for_100_apy": 2378351.999999998,
    "sol_equivalent_for_100_apy": 3.230042247635529,
    "daily_sol_for_100_apy": 0.008849430815439806
  },
  {
    "owner": "DKiqtUZBQrKWep7vVifxcS38BE9r3V7Uh7ogvXZznp3Z",
    "amount": 375666.690595826,
    "percentage": 0.5980467537857964,
    "double_amount_for_100_apy": 751333.381191652,
    "sol_equivalent_for_100_apy": 1.0203866220424427,
    "daily_sol_for_100_apy": 0.0027955797864176513
  },
  {
    "owner": "FpGFCJa5FnPRWRDrLgF2M6F6Wh3H9akLNdXv8gqdwhVo",
    "amount": 59005.955954836,
    "percentage": 0.09393518588738416,
    "double_amount_for_100_apy": 118011.911909672,
    "sol_equivalent_for_100_apy": 0.16027209647372773,
    "daily_sol_for_100_apy": 0.0004391016341745965
  },
  {
    "owner": "8Veq3G65cAv88foMN4yWNwd8z1visrpkCpmhuu9iaSJP",
    "amount": 84363.903136172,
    "percentage": 0.13430405109184734,
    "double_amount_for_100_apy": 168727.806272344,
    "sol_equivalent_for_100_apy": 0.22914940370917952,
    "daily_sol_for_100_apy": 0.0006278065855046015
  },
  {
    "owner": "HdTyU6wjJAxP3Xqq5EbSobHbREvuGbVu5NL55dGcY4qY",
    "amount": 49606.750160154,
    "percentage": 0.07897201599665264,
    "double_amount_for_100_apy": 99213.500320308,
    "sol_equivalent_for_100_apy": 0.1347419547528693,
    "daily_sol_for_100_apy": 0.00036915604041881997
  },
  {
    "owner": "596PuCJq33Bn6J5ZRyVdTU9zD27K6rqfHUMGQVMPiKDi",
    "amount": 1189442.722364975,
    "percentage": 1.8935465313581281,
    "double_amount_for_100_apy": 2378885.44472995,
    "sol_equivalent_for_100_apy": 3.230766719460777,
    "daily_sol_for_100_apy": 0.008851415669755554
  },
  {
    "owner": "CDB5mDxYAvhzEdb5rG7SaHCSv4hLAEeuAM9ZMvTjpRuP",
    "amount": 22120.982346468,
    "percentage": 0.03521574314154827,
    "double_amount_for_100_apy": 44241.964692936,
    "sol_equivalent_for_100_apy": 0.06008505682782988,
    "daily_sol_for_100_apy": 0.00016461659404884898
  },
  {
    "owner": "EHeVLBy8YqwgEjYcsE8ARvKjuwVqqVWVbgNLhpH3fyeB",
    "amount": 66736.891425784,
    "percentage": 0.10624253433713592,
    "double_amount_for_100_apy": 133473.782851568,
    "sol_equivalent_for_100_apy": 0.1812708789793502,
    "daily_sol_for_100_apy": 0.0004966325451489046
  },
  {
    "owner": "CzX9GsBrdBQXAyTfSJyi3eKF4N9JDwj5VSZ5B6pFFZ5B",
    "amount": 1139947.999999999,
    "percentage": 1.8147528592522628,
    "double_amount_for_100_apy": 2279895.999999998,
    "sol_equivalent_for_100_apy": 3.09632905483093,
    "daily_sol_for_100_apy": 0.008483093300906658
  },
  {
    "owner": "6QyRXcK21uo3dXZwbFm1N6Dupi4XN3BpTDkWwPei65fC",
    "amount": 88263.836155688,
    "percentage": 0.14051259270783245,
    "double_amount_for_100_apy": 176527.672311376,
    "sol_equivalent_for_100_apy": 0.23974240963596033,
    "daily_sol_for_100_apy": 0.0006568285195505762
  },
  {
    "owner": "QDZkCqMUkEcUB7JdCpAc3guZQieAJ5aiW8UkC7AZkHu",
    "amount": 1189175.999999999,
    "percentage": 1.8931219197315747,
    "double_amount_for_100_apy": 2378351.999999998,
    "sol_equivalent_for_100_apy": 3.230042247635529,
    "daily_sol_for_100_apy": 0.008849430815439806
  },
  {
    "owner": "CLaHgfzRzVfkEZESRjVg1yCxMR1Jpuu2P34jv9f58piR",
    "amount": 79457.2204673,
    "percentage": 0.1264928032079272,
    "double_amount_for_100_apy": 158914.4409346,
    "sol_equivalent_for_100_apy": 0.21582186235600925,
    "daily_sol_for_100_apy": 0.0005912927735781076
  },
  {
    "owner": "5NMb27gbokooTpno5itgqBa4pSU2bQxZk4kqQarrBfds",
    "amount": 62172.013692412,
    "percentage": 0.09897542661049066,
    "double_amount_for_100_apy": 124344.027384824,
    "sol_equivalent_for_100_apy": 0.16887174888079268,
    "daily_sol_for_100_apy": 0.00046266232570080186
  },
  {
    "owner": "BqhVUXVBtYeh4bdWwKJKfaffi1GstBR8hsBr9VTA2oAw",
    "amount": 41725.775725598,
    "percentage": 0.06642581135503348,
    "double_amount_for_100_apy": 83451.551451196,
    "sol_equivalent_for_100_apy": 0.11333563611193523,
    "daily_sol_for_100_apy": 0.00031050859208749376
  },
  {
    "owner": "5LmkWykmDykfjZEQwCiTNUzhJwMaNx9Zqtw5k7MYi3KG",
    "amount": 249429.879592311,
    "percentage": 0.397082662694346,
    "double_amount_for_100_apy": 498859.759184622,
    "sol_equivalent_for_100_apy": 0.6775019416014183,
    "daily_sol_for_100_apy": 0.0018561697030175844
  },
  {
    "owner": "2S1kLZqWPFpa9bmJ5K9CFb8fHjRQ9t4XCskMp9AZodNi",
    "amount": 42865.100663788,
    "percentage": 0.06823957232412829,
    "double_amount_for_100_apy": 85730.201327576,
    "sol_equivalent_for_100_apy": 0.11643027280502222,
    "daily_sol_for_100_apy": 0.0003189870487808828
  },
  {
    "owner": "7uieVDziL6ash997w57dzc5ct5VAhky1d4a2WL1Dhmuu",
    "amount": 84079.014382716,
    "percentage": 0.13385051928170946,
    "double_amount_for_100_apy": 168158.028765432,
    "sol_equivalent_for_100_apy": 0.22837558830293261,
    "daily_sol_for_100_apy": 0.0006256865432957058
  },
  {
    "owner": "H3NHCLKceUp2LiQbsfekm6y2mtz6RAyUGg45HrApHQaZ",
    "amount": 340016.936273206,
    "percentage": 0.5412937320790032,
    "double_amount_for_100_apy": 680033.872546412,
    "sol_equivalent_for_100_apy": 0.9235546875097157,
    "daily_sol_for_100_apy": 0.0025302868150951117
  },
  {
    "owner": "6AiKWmYLF4hN3tiBU4g14LXkiHvKo6Bnge3h7vEMbgBF",
    "amount": 59215.093544188,
    "percentage": 0.09426812479183741,
    "double_amount_for_100_apy": 118430.187088376,
    "sol_equivalent_for_100_apy": 0.16084015641538113,
    "daily_sol_for_100_apy": 0.0004406579627818661
  },
  {
    "owner": "7f2gGGX9Exc7mfNSbxEoyt2ScSaa17kYLD73kva1jyUu",
    "amount": 228702.654680179,
    "percentage": 0.3640857271554826,
    "double_amount_for_100_apy": 457405.309360358,
    "sol_equivalent_for_100_apy": 0.6212026115254413,
    "daily_sol_for_100_apy": 0.0017019249630834008
  },
  {
    "owner": "48UZG62TRGSEfSELMTqMP5z5WWi5buBQtzMjvyvrjG9s",
    "amount": 87954.829164157,
    "percentage": 0.14002066560114879,
    "double_amount_for_100_apy": 175909.658328314,
    "sol_equivalent_for_100_apy": 0.23890308422285084,
    "daily_sol_for_100_apy": 0.0006545289978708242
  },
  {
    "owner": "CQ5Av6vkg67ytBCK2xYS2wFJStUppcpW2jHC7Y1i7pdm",
    "amount": 153191.901921715,
    "percentage": 0.24387554697821717,
    "double_amount_for_100_apy": 306383.80384343,
    "sol_equivalent_for_100_apy": 0.4161001527131209,
    "daily_sol_for_100_apy": 0.0011400004183921121
  },
  {
    "owner": "9S5oDjU1FkbX1GjR5wrvkD159CY6Q8JuPEjqotQtESLA",
    "amount": 54833.572914615,
    "percentage": 0.08729291443979469,
    "double_amount_for_100_apy": 109667.14582923,
    "sol_equivalent_for_100_apy": 0.1489390612516649,
    "daily_sol_for_100_apy": 0.0004080522226073011
  },
  {
    "owner": "AeLdhWxM8zmLnK6eKMZkQhCFEr5HxoyQbvjuQ92xa2LE",
    "amount": 438860.796122777,
    "percentage": 0.6986493108260504,
    "double_amount_for_100_apy": 877721.592245554,
    "sol_equivalent_for_100_apy": 1.1920345788239364,
    "daily_sol_for_100_apy": 0.0032658481611614696
  },
  {
    "owner": "3GL5LyxFbF7GXhnAKcNRkbUEJ3iXZduZYR96etnNrPx5",
    "amount": 82696.709077339,
    "percentage": 0.1316499430227112,
    "double_amount_for_100_apy": 165393.418154678,
    "sol_equivalent_for_100_apy": 0.22462096784683658,
    "daily_sol_for_100_apy": 0.0006153999119091413
  },
  {
    "owner": "CQv7EXrj7N9g9ciKeQeJDkPC7SyXawTPV3T6vGEAmpLp",
    "amount": 83810.925671716,
    "percentage": 0.1334237324854516,
    "double_amount_for_100_apy": 167621.851343432,
    "sol_equivalent_for_100_apy": 0.22764740520586021,
    "daily_sol_for_100_apy": 0.0006236915211119458
  },
  {
    "owner": "FG4662UCtZFjqpe33s71sN2iyxqZAxpA27arf6bUD4AG",
    "amount": 85777.033542147,
    "percentage": 0.13655369971155581,
    "double_amount_for_100_apy": 171554.067084294,
    "sol_equivalent_for_100_apy": 0.2329877513656388,
    "daily_sol_for_100_apy": 0.0006383226064812022
  },
  {
    "owner": "EjL7X5YvJVZmwjtbePR6BhFR59LF51w2PgUTHAs1MbN5",
    "amount": 78084.943287668,
    "percentage": 0.12430819133490861,
    "double_amount_for_100_apy": 156169.886575336,
    "sol_equivalent_for_100_apy": 0.21209448031527053,
    "daily_sol_for_100_apy": 0.0005810807679870425
  },
  {
    "owner": "8ixEiWWNpum38cEVtxPbMdkhjwd6FyFiHVDBR5htFpok",
    "amount": 84948.346685107,
    "percentage": 0.13523446248035045,
    "double_amount_for_100_apy": 169896.693370214,
    "sol_equivalent_for_100_apy": 0.2307368704545714,
    "daily_sol_for_100_apy": 0.0006321558094645792
  },
  {
    "owner": "A8wzugnC1Kgeyackjyddz784QTG7VBekzEAeMmuLyMiu",
    "amount": 84856.446045667,
    "percentage": 0.1350881602383264,
    "double_amount_for_100_apy": 169712.892091334,
    "sol_equivalent_for_100_apy": 0.23048724975252569,
    "daily_sol_for_100_apy": 0.0006314719171302074
  },
  {
    "owner": "GZtd6uxVTtuWpHfoGNbq4DDCYadPvFDvDakWVZyn6xfk",
    "amount": 84900.403217904,
    "percentage": 0.13515813834610124,
    "double_amount_for_100_apy": 169800.806435808,
    "sol_equivalent_for_100_apy": 0.23060664631233857,
    "daily_sol_for_100_apy": 0.0006317990309927085
  },
  {
    "owner": "DAEWtrSrUieacgRDt46ZmWCs7kYtiGP7s4dYqCGyb8Gq",
    "amount": 85262.696127043,
    "percentage": 0.13573489456019772,
    "double_amount_for_100_apy": 170525.392254086,
    "sol_equivalent_for_100_apy": 0.23159070704223708,
    "daily_sol_for_100_apy": 0.0006344950877869509
  },
  {
    "owner": "H9818nzG9mSndrCX5SR4ZRzEK9x1NjFmeYDbDVUijW1x",
    "amount": 757558.302820522,
    "percentage": 1.2060033405855661,
    "double_amount_for_100_apy": 1515116.605641044,
    "sol_equivalent_for_100_apy": 2.057681388757726,
    "daily_sol_for_100_apy": 0.005637483256870483
  },
  {
    "owner": "5auQXsuxhEpumHFTSaZ5QfiipWG6xGmrtELyjD8gYfTz",
    "amount": 84179.400417321,
    "percentage": 0.13401032994265924,
    "double_amount_for_100_apy": 168358.800834642,
    "sol_equivalent_for_100_apy": 0.2286482570524253,
    "daily_sol_for_100_apy": 0.0006264335809655488
  },
  {
    "owner": "7v1rebHZmKx84XPLs1WyvDdvHBLTjPrpoiDEUEVZLC1v",
    "amount": 235826.574339139,
    "percentage": 0.37542673005226485,
    "double_amount_for_100_apy": 471653.148678278,
    "sol_equivalent_for_100_apy": 0.6405526164592797,
    "daily_sol_for_100_apy": 0.0017549386752309035
  },
  {
    "owner": "6zuPCYF33Xwh4AhsC4QZiXWYffe3y1hNJvhdKxTAqZQj",
    "amount": 83373.951812722,
    "percentage": 0.1327280871051116,
    "double_amount_for_100_apy": 166747.903625444,
    "sol_equivalent_for_100_apy": 0.22646049592946807,
    "daily_sol_for_100_apy": 0.000620439714875255
  },
  {
    "owner": "DnX5B6kqDDzpbq2B46duxJqrFNji7aP2kLBcDiGcXvbB",
    "amount": 63160.617628846,
    "percentage": 0.10054924560952538,
    "double_amount_for_100_apy": 126321.235257692,
    "sol_equivalent_for_100_apy": 0.17155699688517606,
    "daily_sol_for_100_apy": 0.00047001916954842756
  },
  {
    "owner": "Bu9RTZsdUDE5VdVYcY7TuChkDdN2hqQKaqtqqPv8P6v",
    "amount": 83283.229076512,
    "percentage": 0.13258366003919606,
    "double_amount_for_100_apy": 166566.458153024,
    "sol_equivalent_for_100_apy": 0.22621407465054935,
    "daily_sol_for_100_apy": 0.0006197645880836968
  },
  {
    "owner": "2hKuLYRaiiBVa7eiiYLJiBPUVVT2qoBH7VEQjP3A2ayX",
    "amount": 77566.507467374,
    "percentage": 0.12348286168196188,
    "double_amount_for_100_apy": 155133.014934748,
    "sol_equivalent_for_100_apy": 0.2106863038954326,
    "daily_sol_for_100_apy": 0.0005772227503984455
  },
  {
    "owner": "JA2SRHpThp4hQNM9537n9138RqiKmSddt6grWFK6viYS",
    "amount": 85148.601841843,
    "percentage": 0.13555326089770514,
    "double_amount_for_100_apy": 170297.203683686,
    "sol_equivalent_for_100_apy": 0.23128080391485326,
    "daily_sol_for_100_apy": 0.0006336460381228857
  },
  {
    "owner": "FZjutB3bDfV8fXy6f3eYkQLbQZamF8942L9DXGCyv47c",
    "amount": 77938.988567685,
    "percentage": 0.12407583709996936,
    "double_amount_for_100_apy": 155877.97713537,
    "sol_equivalent_for_100_apy": 0.21169803781072377,
    "daily_sol_for_100_apy": 0.0005799946241389693
  },
  {
    "owner": "EemYx31Vm5LqLQDdLKsL2KFYmkpRwjaKx1JfvUG3Foyg",
    "amount": 140633.919692611,
    "percentage": 0.22388372791567612,
    "double_amount_for_100_apy": 281267.839385222,
    "sol_equivalent_for_100_apy": 0.38199013607549775,
    "daily_sol_for_100_apy": 0.0010465483180150624
  },
  {
    "owner": "Z2x1gARyVRqmoqjTxUhyC13eupAXcHJWiQLxGzgW8R3",
    "amount": 83979.285749079,
    "percentage": 0.13369175517752044,
    "double_amount_for_100_apy": 167958.571498158,
    "sol_equivalent_for_100_apy": 0.228104705187274,
    "daily_sol_for_100_apy": 0.0006249443977733534
  },
  {
    "owner": "FzKviPkXJD3cmu9FNjaC5QWUXJqKPrzkcGDXKBoFvH5d",
    "amount": 3621271.904252713,
    "percentage": 5.764923963525093,
    "double_amount_for_100_apy": 7242543.808505426,
    "sol_equivalent_for_100_apy": 9.836106043942895,
    "daily_sol_for_100_apy": 0.026948235736829848
  },
  {
    "owner": "5tZyijHeRDimLDRMLwh7TgRSCT4iVLa1RsXHMsD3N6ay",
    "amount": 370949.919962814,
    "percentage": 0.5905378384732596,
    "double_amount_for_100_apy": 741899.839925628,
    "sol_equivalent_for_100_apy": 1.0075749201437874,
    "daily_sol_for_100_apy": 0.0027604792332706503
  },
  {
    "owner": "z4YDgTE1LGe6N6qByLdBRmKc1Wym9DMSGry7vC7Xbtz",
    "amount": 78477.022688161,
    "percentage": 0.12493236648421241,
    "double_amount_for_100_apy": 156954.045376322,
    "sol_equivalent_for_100_apy": 0.2131594471730107,
    "daily_sol_for_100_apy": 0.0005839984854055087
  },
  {
    "owner": "B2bdRh5atvnTRL8ELJLkbu8TM7nuEDLQ8Ud1rD9wX5vA",
    "amount": 85639.576912109,
    "percentage": 0.13633487410513812,
    "double_amount_for_100_apy": 171279.153824218,
    "sol_equivalent_for_100_apy": 0.23261439139012605,
    "daily_sol_for_100_apy": 0.0006372997024387015
  },
  {
    "owner": "2qN1GwmgbsGb3Rsb3PAtLaLdXpMjwakgDjFJwCwHbdHd",
    "amount": 83552.284815814,
    "percentage": 0.1330119863068824,
    "double_amount_for_100_apy": 167104.569631628,
    "sol_equivalent_for_100_apy": 0.2269448843918444,
    "daily_sol_for_100_apy": 0.0006217668065529984
  },
  {
    "owner": "42eK9KwtLnibpzACAcDace7wxNp8evxhBAg8oVHLW3EC",
    "amount": 54960.914159167,
    "percentage": 0.08749563674612049,
    "double_amount_for_100_apy": 109921.828318334,
    "sol_equivalent_for_100_apy": 0.14928494579673596,
    "daily_sol_for_100_apy": 0.00040899985149790675
  },
  {
    "owner": "FFxVkf2W9gWmbourzpZwC3zDizjjPPg8mhRQpWq1gcL2",
    "amount": 525518.304745976,
    "percentage": 0.8366046926062967,
    "double_amount_for_100_apy": 1051036.609491952,
    "sol_equivalent_for_100_apy": 1.427413878379068,
    "daily_sol_for_100_apy": 0.0039107229544632
  },
  {
    "owner": "6tNWNPknqvToHVYhL6iDwCuFhh1YjEcZPcd4FaP9EQW1",
    "amount": 77780.15741346,
    "percentage": 0.12382298408275441,
    "double_amount_for_100_apy": 155560.31482692,
    "sol_equivalent_for_100_apy": 0.21126662030954022,
    "daily_sol_for_100_apy": 0.000578812658382302
  },
  {
    "owner": "BBqdZKN15A1oj15xHoy5FcaZeRpaSxEnkVpwDns9mycM",
    "amount": 84982.419821851,
    "percentage": 0.13528870558822015,
    "double_amount_for_100_apy": 169964.839643702,
    "sol_equivalent_for_100_apy": 0.23082941997725986,
    "daily_sol_for_100_apy": 0.000632409369800712
  },
  {
    "owner": "4aoDxFK1BXADhEfmq2gXbXVQkNQd5GPNAExs6PBTnaGh",
    "amount": 87185.888203673,
    "percentage": 0.13879654151247586,
    "double_amount_for_100_apy": 174371.776407346,
    "sol_equivalent_for_100_apy": 0.2368144852364092,
    "daily_sol_for_100_apy": 0.0006488068088668744
  },
  {
    "owner": "AFYVx1QHny6YjVa6Ks4rbwMgA3vcYvMCCMF793vbMPFR",
    "amount": 48032.055218606,
    "percentage": 0.07646516292298235,
    "double_amount_for_100_apy": 96064.110437212,
    "sol_equivalent_for_100_apy": 0.1304647651793007,
    "daily_sol_for_100_apy": 0.0003574377128200019
  },
  {
    "owner": "ATvAMJwdvzSidrxdrcjYaQkGEFu2tLcaWjkFx6Wqf47f",
    "amount": 85849.471679024,
    "percentage": 0.136669018406809,
    "double_amount_for_100_apy": 171698.943358048,
    "sol_equivalent_for_100_apy": 0.23318450797900195,
    "daily_sol_for_100_apy": 0.0006388616656958958
  },
  {
    "owner": "E4KTvsgSjLj3aCxLhRUyVzujNjx8VJieHjy3sDijN4hx",
    "amount": 61140.000003585,
    "percentage": 0.09733250097477195,
    "double_amount_for_100_apy": 122280.00000717,
    "sol_equivalent_for_100_apy": 0.1660685912194798,
    "daily_sol_for_100_apy": 0.00045498244169720495
  },
  {
    "owner": "7m7TfFwKWuWtVuy4emWNChY8SJPwGjBZ6iLT2betFPJ5",
    "amount": 1189510.328999999,
    "percentage": 1.893654158490431,
    "double_amount_for_100_apy": 2379020.657999998,
    "sol_equivalent_for_100_apy": 3.230950352739071,
    "daily_sol_for_100_apy": 0.008851918774627592
  },
  {
    "owner": "G91Jq6HUt4M3tZrKgrVZuemtkMp1ro5zynreT7CT98Ep",
    "amount": 358441.914020513,
    "percentage": 0.5706255797146714,
    "double_amount_for_100_apy": 716883.828041026,
    "sol_equivalent_for_100_apy": 0.973600649197091,
    "daily_sol_for_100_apy": 0.0026673990388961398
  },
  {
    "owner": "6wiDe9s5NbeVJSe4AjqWhrUFPVNAu7XyamLQAEok3Ejt",
    "amount": 1237360.934860188,
    "percentage": 1.969830461095226,
    "double_amount_for_100_apy": 2474721.869720376,
    "sol_equivalent_for_100_apy": 3.3609222648053816,
    "daily_sol_for_100_apy": 0.00920800620494625
  },
  {
    "owner": "HEJ79d6rV6FMBgRXwDYmYHYUPEtnGBy5Zo9uAUAqntqS",
    "amount": 824805.378522958,
    "percentage": 1.3130580684392483,
    "double_amount_for_100_apy": 1649610.757045916,
    "sol_equivalent_for_100_apy": 2.2403380312974455,
    "daily_sol_for_100_apy": 0.006137912414513549
  },
  {
    "owner": "HvwnSN9PskkMHheJEwPAFT4Av4uNcw9Ychw8KaC1Wbbi",
    "amount": 77927.32166091,
    "percentage": 0.12405726383835697,
    "double_amount_for_100_apy": 155854.64332182,
    "sol_equivalent_for_100_apy": 0.21166634813503032,
    "daily_sol_for_100_apy": 0.0005799078031096721
  },
  {
    "owner": "CXdzKKn2ZSaaapjgzUJpJsKcDD1ARVPbx52e8evSo4fp",
    "amount": 44257.505251099,
    "percentage": 0.07045622624699022,
    "double_amount_for_100_apy": 88515.010502198,
    "sol_equivalent_for_100_apy": 0.12021232495105952,
    "daily_sol_for_100_apy": 0.0003293488354823548
  },
  {
    "owner": "2JruZtz6cxBEDm45tT4h37tYZdjEq2yX7cY4F8BTQNBY",
    "amount": 268089.647019959,
    "percentage": 0.4267882863651683,
    "double_amount_for_100_apy": 536179.294039918,
    "sol_equivalent_for_100_apy": 0.7281856394916856,
    "daily_sol_for_100_apy": 0.001995029149292289
  },
  {
    "owner": "ECNQ82uFZ6ZjeMG45SpdSMUUX73ZkLZqg8GL1pv9gwxH",
    "amount": 50119.852872961,
    "percentage": 0.0797888555499977,
    "double_amount_for_100_apy": 100239.705745922,
    "sol_equivalent_for_100_apy": 0.13613564537540374,
    "daily_sol_for_100_apy": 0.0003729743708915171
  },
  {
    "owner": "BaX37KNmPPaj5AspazbvygAfkhKZ4PLiezrDYV6P5mL4",
    "amount": 353170.449481898,
    "percentage": 0.5622336132882216,
    "double_amount_for_100_apy": 706340.898963796,
    "sol_equivalent_for_100_apy": 0.9592822865942138,
    "daily_sol_for_100_apy": 0.002628170648203325
  },
  {
    "owner": "9kcdtMJQMvBDnMxDEGgAjZUaE7XahubFzmQJMjMX172P",
    "amount": 83968.185538832,
    "percentage": 0.13367408407472972,
    "double_amount_for_100_apy": 167936.371077664,
    "sol_equivalent_for_100_apy": 0.22807455477383184,
    "daily_sol_for_100_apy": 0.0006248617939009092
  },
  {
    "owner": "68AT5oxAdKtbRXa9Y9wacyJSwDw5s51EmuuRDrH6veB5",
    "amount": 84172.492760329,
    "percentage": 0.13399933322151322,
    "double_amount_for_100_apy": 168344.985520658,
    "sol_equivalent_for_100_apy": 0.22862949446058328,
    "daily_sol_for_100_apy": 0.0006263821766043378
  },
  {
    "owner": "EAdq2omMxJhLmriAy2oZxyhS9q5bip6K3YdKTTGm6BXw",
    "amount": 33577.170673797,
    "percentage": 0.05345354918458946,
    "double_amount_for_100_apy": 67154.341347594,
    "sol_equivalent_for_100_apy": 0.09120237864910924,
    "daily_sol_for_100_apy": 0.0002498695305455048
  },
  {
    "owner": "J9fPCLypwGiGr3ZMsuPr9zLov2UamdzxUicmDZURpuU2",
    "amount": 84413.916621264,
    "percentage": 0.13438367061402895,
    "double_amount_for_100_apy": 168827.833242528,
    "sol_equivalent_for_100_apy": 0.22928525043817394,
    "daily_sol_for_100_apy": 0.0006281787683237642
  },
  {
    "owner": "4mtzamBuW9nQ7NBk15QhaKXUpvS2tVZXA4kzU4kwvmYg",
    "amount": 991011.273999999,
    "percentage": 1.577651386767403,
    "double_amount_for_100_apy": 1982022.547999998,
    "sol_equivalent_for_100_apy": 2.6917868195314307,
    "daily_sol_for_100_apy": 0.007374758409675153
  },
  {
    "owner": "3B9jAmdtCHW8a35G8HqC78dinLfoxUtc3pasqMqfNDjo",
    "amount": 84527.341843031,
    "percentage": 0.13456423915357021,
    "double_amount_for_100_apy": 169054.683686062,
    "sol_equivalent_for_100_apy": 0.22959333625411274,
    "daily_sol_for_100_apy": 0.0006290228390523636
  },
  {
    "owner": "12jXbYZNKgSsfatkD1FWRC9EG7Qr9akqU2vv8wneFkMe",
    "amount": 532385.566662255,
    "percentage": 0.8475371063635921,
    "double_amount_for_100_apy": 1064771.13332451,
    "sol_equivalent_for_100_apy": 1.4460667490350176,
    "daily_sol_for_100_apy": 0.00396182670968498
  },
  {
    "owner": "HFXKmrzmGt8UgYbYBisUEzpcNAETseCqAi5mQjHwNHQC",
    "amount": 84800.135510829,
    "percentage": 0.13499851605797494,
    "double_amount_for_100_apy": 169600.271021658,
    "sol_equivalent_for_100_apy": 0.2303342989643213,
    "daily_sol_for_100_apy": 0.0006310528738748529
  },
  {
    "owner": "HLnpSz9h2S4hiLQ43rnSD9XkcUThA7B8hQMKmDaiTLcC",
    "amount": 35233.1012334,
    "percentage": 0.05608972620122771,
    "double_amount_for_100_apy": 70466.2024668,
    "sol_equivalent_for_100_apy": 0.09570022057214538,
    "daily_sol_for_100_apy": 0.0002621923851291654
  },
  {
    "owner": "E9mNQqUicjt876kNYUivojW4pSwyDvsuQNXGxV79kqm3",
    "amount": 2004687,
    "percentage": 3.1913836992177225,
    "double_amount_for_100_apy": 4009374,
    "sol_equivalent_for_100_apy": 5.4451348692588235,
    "daily_sol_for_100_apy": 0.014918177723996777
  },
  {
    "owner": "2nLBJVQjJCJAkMDw1aKGBHfM6qXdRFQA9PmZbWSMQz18",
    "amount": 83192.398586992,
    "percentage": 0.1324390614342038,
    "double_amount_for_100_apy": 166384.797173984,
    "sol_equivalent_for_100_apy": 0.22596736069187293,
    "daily_sol_for_100_apy": 0.0006190886594297888
  },
  {
    "owner": "ABFh3exo6T5PAa84egnFuh9sb3ZEukb64gF9BTr4fYQN",
    "amount": 77693.112518291,
    "percentage": 0.12368441199666694,
    "double_amount_for_100_apy": 155386.225036582,
    "sol_equivalent_for_100_apy": 0.21103018878986873,
    "daily_sol_for_100_apy": 0.0005781649007941609
  },
  {
    "owner": "45uHGcerR18ZqTVZGtZkxL8MZXMkLjsMqqdNUSGQaerZ",
    "amount": 2174620.548879351,
    "percentage": 3.4619112967148773,
    "double_amount_for_100_apy": 4349241.097758702,
    "sol_equivalent_for_100_apy": 5.906708717176156,
    "daily_sol_for_100_apy": 0.016182763608701797
  },
  {
    "owner": "3vCsgkAmHEipvdpW45AVyDG2s1erWhuftma1J7wMRmf2",
    "amount": 85648.964792664,
    "percentage": 0.13634981924568798,
    "double_amount_for_100_apy": 171297.929585328,
    "sol_equivalent_for_100_apy": 0.23263989077020808,
    "daily_sol_for_100_apy": 0.0006373695637539947
  },
  {
    "owner": "BJjpgZYnrdXpMoAE1chy16UNJoG1CLgTYag6pcTtj7dh",
    "amount": 47212.750067444,
    "percentage": 0.07516086100248129,
    "double_amount_for_100_apy": 94425.500134888,
    "sol_equivalent_for_100_apy": 0.1282393668766452,
    "daily_sol_for_100_apy": 0.00035134073116889096
  },
  {
    "owner": "UkFYxgVPxz4YNELAHaGh3aeRWKmEqegTevaCDdfqdJu",
    "amount": 84047.558028794,
    "percentage": 0.13380044199027016,
    "double_amount_for_100_apy": 168095.116057588,
    "sol_equivalent_for_100_apy": 0.22829014649101861,
    "daily_sol_for_100_apy": 0.0006254524561397771
  },
  {
    "owner": "AtKYpjYmNPwC2uBsPEHbVNUXoE2nftfUSTRiwWcjcdb5",
    "amount": 333391.862042196,
    "percentage": 0.5307468716928417,
    "double_amount_for_100_apy": 666783.724084392,
    "sol_equivalent_for_100_apy": 0.9055596475325518,
    "daily_sol_for_100_apy": 0.0024809853357056215
  },
  {
    "owner": "CvxkiiPuVUsRPMWQou2qBzB6Ssxjpiix14yFj5FMKxrW",
    "amount": 82392.936443315,
    "percentage": 0.13116634880950356,
    "double_amount_for_100_apy": 164785.87288663,
    "sol_equivalent_for_100_apy": 0.22379586000613594,
    "daily_sol_for_100_apy": 0.0006131393424825642
  },
  {
    "owner": "DA7iMX8acSwZGcu1PZ2KHWLpp943VQAyYxi67LqhzjCb",
    "amount": 390877.618708431,
    "percentage": 0.622261959465556,
    "double_amount_for_100_apy": 781755.237416862,
    "sol_equivalent_for_100_apy": 1.0617025756350658,
    "daily_sol_for_100_apy": 0.002908774179822098
  },
  {
    "owner": "4dUQNcV61gN9Geh5y2wQuwu4sxkdiQxixx4DCVSbos7T",
    "amount": 82954.994821889,
    "percentage": 0.13206112387782587,
    "double_amount_for_100_apy": 165909.989643778,
    "sol_equivalent_for_100_apy": 0.2253225241066825,
    "daily_sol_for_100_apy": 0.0006173219838539246
  },
  {
    "owner": "G8WCFY8HUGywg6PcW8ayfJh1xG9sB1YBuhRcGK8yRJEk",
    "amount": 47381.870046209,
    "percentage": 0.07543009342801338,
    "double_amount_for_100_apy": 94763.740092418,
    "sol_equivalent_for_100_apy": 0.1286987309037784,
    "daily_sol_for_100_apy": 0.0003525992627500778
  },
  {
    "owner": "GwGSoymm1cE4MkZjVj4faFcXhDWUqm1nP5CAVqT9QveA",
    "amount": 220875.481233553,
    "percentage": 0.35162517159318685,
    "double_amount_for_100_apy": 441750.962467106,
    "sol_equivalent_for_100_apy": 0.5999424272363428,
    "daily_sol_for_100_apy": 0.0016436778828392954
  },
  {
    "owner": "ABj7j2dJao3sQp7t73PnMvgztVfUbPfpyQfpykFYvnDZ",
    "amount": 354512.355432197,
    "percentage": 0.5643698753459232,
    "double_amount_for_100_apy": 709024.710864394,
    "sol_equivalent_for_100_apy": 0.9629271742406339,
    "daily_sol_for_100_apy": 0.002638156641755161
  },
  {
    "owner": "Baw2AgUDqwiRdPmgn6nuajvRtAK2LjCwU58SzZYhNi2V",
    "amount": 377512.962549616,
    "percentage": 0.6009859468955676,
    "double_amount_for_100_apy": 755025.925099232,
    "sol_equivalent_for_100_apy": 1.0254014696439466,
    "daily_sol_for_100_apy": 0.002809319094914922
  },
  {
    "owner": "8D16nTyDWoaKR9zwhohY97wacTj8DmDsWarGUrQgkt5D",
    "amount": 46357.58096817,
    "percentage": 0.07379946507209527,
    "double_amount_for_100_apy": 92715.16193634,
    "sol_equivalent_for_100_apy": 0.12591655484585457,
    "daily_sol_for_100_apy": 0.00034497686259138237
  },
  {
    "owner": "4cUyKneVRn7npmjLFigJvJUZwn6qr6x5Wm66UtNaiKoK",
    "amount": 48132.328540426,
    "percentage": 0.07662479414956423,
    "double_amount_for_100_apy": 96264.657080852,
    "sol_equivalent_for_100_apy": 0.13073712777809968,
    "daily_sol_for_100_apy": 0.00035818391172082105
  },
  {
    "owner": "w1RgmsVQkyS6FGuaLykAhwK5x3RJb8jLYnDHyJ4cp4j",
    "amount": 261965.18493864,
    "percentage": 0.41703838104189417,
    "double_amount_for_100_apy": 523930.36987728,
    "sol_equivalent_for_100_apy": 0.7115503632443495,
    "daily_sol_for_100_apy": 0.0019494530499845192
  },
  {
    "owner": "6ZnHXdEGCP5VUuRaPqnWjVYCrvAKvr1UL6biaNdLo2mp",
    "amount": 385018.82151716,
    "percentage": 0.6129349823098977,
    "double_amount_for_100_apy": 770037.64303432,
    "sol_equivalent_for_100_apy": 1.0457888988974475,
    "daily_sol_for_100_apy": 0.002865175065472459
  },
  {
    "owner": "7txmSTPVWVKgH8T29VyUmNGEKKDuTkBDYawxaSBhm1KC",
    "amount": 83290.55953797,
    "percentage": 0.13259532984860012,
    "double_amount_for_100_apy": 166581.11907594,
    "sol_equivalent_for_100_apy": 0.22623398566473396,
    "daily_sol_for_100_apy": 0.0006198191388074903
  },
  {
    "owner": "ErkiFz9HFtVXG99EzdZ3cvXvHzHqKQYJnkpnQ8f3852f",
    "amount": 30575.499385908,
    "percentage": 0.048675005292910196,
    "double_amount_for_100_apy": 61150.998771816,
    "sol_equivalent_for_100_apy": 0.08304923304795682,
    "daily_sol_for_100_apy": 0.000227532145336868
  },
  {
    "owner": "9EkAmGeJ3aFBijxKdWAZ6HWPBXeortX9BT8Wmu7J1dJD",
    "amount": 83520.271983506,
    "percentage": 0.13296102312350588,
    "double_amount_for_100_apy": 167040.543967012,
    "sol_equivalent_for_100_apy": 0.22685793107221694,
    "daily_sol_for_100_apy": 0.0006215285782800465
  },
  {
    "owner": "HtEWNdyGkZxqQvND4vcEceSzJTjBkvjqsy2HBxx2sCC5",
    "amount": 88004.935598817,
    "percentage": 0.14010043309542589,
    "double_amount_for_100_apy": 176009.871197634,
    "sol_equivalent_for_100_apy": 0.23903918342164918,
    "daily_sol_for_100_apy": 0.0006549018723880799
  },
  {
    "owner": "4mVoMoUcwW48mpUNVSomjbAEopxBiKEHK5kB8xQT5ooh",
    "amount": 20367.287,
    "percentage": 0.03242392838836637,
    "double_amount_for_100_apy": 40734.574,
    "sol_equivalent_for_100_apy": 0.05532166599369475,
    "daily_sol_for_100_apy": 0.00015156620820190342
  },
  {
    "owner": "6hwDekJfomsimdKQbkdZrDAnV34ygazMHQ4uzDrPsACo",
    "amount": 102124.028,
    "percentage": 0.16257747880724235,
    "double_amount_for_100_apy": 204248.056,
    "sol_equivalent_for_100_apy": 0.27738949065463314,
    "daily_sol_for_100_apy": 0.0007599712072729675
  },
  {
    "owner": "DzMgK5k9t2vnAHctiojF3wZRp1euZEveJAcyKYZgkjxs",
    "amount": 118020.615952422,
    "percentage": 0.18788422827214155,
    "double_amount_for_100_apy": 236041.231904844,
    "sol_equivalent_for_100_apy": 0.32056783488591345,
    "daily_sol_for_100_apy": 0.0008782680407833245
  },
  {
    "owner": "2cy8vkc7Es7yMNu5n7gnr2PM8ikfCRwweWPbUGyjzw66",
    "amount": 83344.653513863,
    "percentage": 0.1326814453533601,
    "double_amount_for_100_apy": 166689.307027726,
    "sol_equivalent_for_100_apy": 0.2263809158310651,
    "daily_sol_for_100_apy": 0.0006202216872083975
  },
  {
    "owner": "3pwLmqsNcNMk7zhXNnkLwDNqdvgdRhQntZcn55C3gy9B",
    "amount": 69499.727108675,
    "percentage": 0.11064086123903903,
    "double_amount_for_100_apy": 138999.45421735,
    "sol_equivalent_for_100_apy": 0.18877529882890395,
    "daily_sol_for_100_apy": 0.0005171925995312437
  },
  {
    "owner": "9Q4SR95AR7arXXAMT4HG6kkmuwZjSXJZovhL2Yf4QCn6",
    "amount": 161097.082138096,
    "percentage": 0.2564602862826257,
    "double_amount_for_100_apy": 322194.164276192,
    "sol_equivalent_for_100_apy": 0.4375722191474277,
    "daily_sol_for_100_apy": 0.0011988279976641856
  },
  {
    "owner": "8wHNDU4WaLttQ3M6SgEXZGW9qFEMi9aoSTGtPvwJbMYa",
    "amount": 40339.654272846,
    "percentage": 0.06421915993790514,
    "double_amount_for_100_apy": 80679.308545692,
    "sol_equivalent_for_100_apy": 0.10957065022864888,
    "daily_sol_for_100_apy": 0.0003001935622702709
  },
  {
    "owner": "79WURBWJWgF2aEohjfMudtdo3JhEpU51NoHi2QU4WqyM",
    "amount": 47719.974708265,
    "percentage": 0.07596834289394748,
    "double_amount_for_100_apy": 95439.94941653,
    "sol_equivalent_for_100_apy": 0.12961709146820571,
    "daily_sol_for_100_apy": 0.00035511531909097454
  },
  {
    "owner": "C6Kbm8TGaCYqLmJexFbowNsKRtYtSx4GsmWs3ZdWsdHq",
    "amount": 85287.474219134,
    "percentage": 0.1357743403186612,
    "double_amount_for_100_apy": 170574.948438268,
    "sol_equivalent_for_100_apy": 0.23165800934590763,
    "daily_sol_for_100_apy": 0.0006346794776600209
  },
  {
    "owner": "DoBGGtypSJvgmwVj1dVKARui52YdWHHEZUmXLjmnkdum",
    "amount": 1239075.999999999,
    "percentage": 1.972560778062558,
    "double_amount_for_100_apy": 2478151.999999998,
    "sol_equivalent_for_100_apy": 3.365580728194347,
    "daily_sol_for_100_apy": 0.009220769118340678
  },
  {
    "owner": "9ZjwoXzhvbRYnBAHs4ySrfmcXEkYNknZ7b5XXnLXdovR",
    "amount": 347339.42673805,
    "percentage": 0.5529508519721238,
    "double_amount_for_100_apy": 694678.8534761,
    "sol_equivalent_for_100_apy": 0.9434440508666574,
    "daily_sol_for_100_apy": 0.002584778221552486
  },
  {
    "owner": "9z3sV8EkCKNgtjpbe3c1uot9J92sn6WciBeVkMZtqVT8",
    "amount": 384919.964066464,
    "percentage": 0.6127776050950521,
    "double_amount_for_100_apy": 769839.928132928,
    "sol_equivalent_for_100_apy": 1.045520382090649,
    "daily_sol_for_100_apy": 0.002864439402988079
  },
  {
    "owner": "9r89sTj1CkHjzKL3A1M5cRKsLdMd4z2YRT5bkXPu65g7",
    "amount": 1182308.789508687,
    "percentage": 1.8821895878408255,
    "double_amount_for_100_apy": 2364617.579017374,
    "sol_equivalent_for_100_apy": 3.2113895166601787,
    "daily_sol_for_100_apy": 0.008798327442904598
  },
  {
    "owner": "ECAe8bm8xnQQN3MKqfRnzsURwxJ27nhN5h6Fkm9jZ4id",
    "amount": 47521.480441029,
    "percentage": 0.07565234774415845,
    "double_amount_for_100_apy": 95042.960882058,
    "sol_equivalent_for_100_apy": 0.12907794093953232,
    "daily_sol_for_100_apy": 0.0003536381943548831
  },
  {
    "owner": "93SXE6KMNrXXZpovjha15yoJSfAc6YFgj8rRE38UMUBs",
    "amount": 47220.61288574,
    "percentage": 0.07517337830325681,
    "double_amount_for_100_apy": 94441.22577148,
    "sol_equivalent_for_100_apy": 0.12826072387954598,
    "daily_sol_for_100_apy": 0.00035139924350560545
  },
  {
    "owner": "D29kmutt7NrAkUqUcSfNeiguf9uquKatttTGoYYGAy5D",
    "amount": 63534.009248055,
    "percentage": 0.10114367053818912,
    "double_amount_for_100_apy": 127068.01849611,
    "sol_equivalent_for_100_apy": 0.17257120395373288,
    "daily_sol_for_100_apy": 0.000472797819051323
  },
  {
    "owner": "6WBwxaSEwmqVe5yviPFMHRgVYMbdAxAG9nej78jyoELC",
    "amount": 83443.213904068,
    "percentage": 0.13283834965946315,
    "double_amount_for_100_apy": 166886.427808136,
    "sol_equivalent_for_100_apy": 0.2266486257615595,
    "daily_sol_for_100_apy": 0.0006209551390727657
  },
  {
    "owner": "C6Bym8Nz9T8pC1UW3PsWQWdyzhUNWKSP3b5mzn4QgPko",
    "amount": 806265.186916455,
    "percentage": 1.2835428048228499,
    "double_amount_for_100_apy": 1612530.37383291,
    "sol_equivalent_for_100_apy": 2.1899791254935423,
    "daily_sol_for_100_apy": 0.005999942809571349
  },
  {
    "owner": "Dn2w1i6ESwTM2SgdZ6H7GpSZhLn5LiMMPSVrBtoirNDt",
    "amount": 284497.968601737,
    "percentage": 0.45290969585583124,
    "double_amount_for_100_apy": 568995.937203474,
    "sol_equivalent_for_100_apy": 0.7727539556382718,
    "daily_sol_for_100_apy": 0.002117134125036361
  },
  {
    "owner": "8RknfWhm9Cw4WDeL9Z8oh3uvRYj3ZEvb6hFESFKa3PB1",
    "amount": 82990.976959111,
    "percentage": 0.13211840604017505,
    "double_amount_for_100_apy": 165981.953918222,
    "sol_equivalent_for_100_apy": 0.2254202588603163,
    "daily_sol_for_100_apy": 0.0006175897503022365
  },
  {
    "owner": "3sE5HnfrktWSWdyQLLVjVVdoUsMk9QU1yN3FPS8PENzG",
    "amount": 84163.150318289,
    "percentage": 0.1339844604173112,
    "double_amount_for_100_apy": 168326.300636578,
    "sol_equivalent_for_100_apy": 0.2286041185006873,
    "daily_sol_for_100_apy": 0.0006263126534265405
  },
  {
    "owner": "EuedL84fVmM5FL7FWmWV9u5TMgf5nL9V9vd4jtyu9k1r",
    "amount": 83718.083078459,
    "percentage": 0.13327593068960347,
    "double_amount_for_100_apy": 167436.166156918,
    "sol_equivalent_for_100_apy": 0.22739522596695855,
    "daily_sol_for_100_apy": 0.0006230006190875577
  },
  {
    "owner": "8g6WUHP8DN6ZKi7DCb4VKZmn5VhTaDKDgkaPorSafMy2",
    "amount": 24314.231082716,
    "percentage": 0.03870730978770886,
    "double_amount_for_100_apy": 48628.462165432,
    "sol_equivalent_for_100_apy": 0.0660423634650764,
    "daily_sol_for_100_apy": 0.00018093798209609972
  },
  {
    "owner": "AJYhaQxosfrhQK4iaTqD8VsYNM5KQKJhQVfdYQmtuLfJ",
    "amount": 93813.162317094,
    "percentage": 0.1493469040258355,
    "double_amount_for_100_apy": 187626.324634188,
    "sol_equivalent_for_100_apy": 0.254815500538611,
    "daily_sol_for_100_apy": 0.0006981246590098932
  },
  {
    "owner": "muMRkJg6ENSB39nBn47oN1ZguAC6JwTsFvxDfMw1MYT",
    "amount": 85467.472943713,
    "percentage": 0.1360608912842241,
    "double_amount_for_100_apy": 170934.945887426,
    "sol_equivalent_for_100_apy": 0.23214692224434377,
    "daily_sol_for_100_apy": 0.0006360189650529966
  },
  {
    "owner": "DiZ7ojw72wLzoue5ZLAATiPVjwS5QRSSkLaa4LJFVqJU",
    "amount": 29569.10637956,
    "percentage": 0.047072866786766476,
    "double_amount_for_100_apy": 59138.21275912,
    "sol_equivalent_for_100_apy": 0.08031566633602437,
    "daily_sol_for_100_apy": 0.00022004292146855992
  },
  {
    "owner": "J6Pay6vWQKcLNkHKfKnyHLvADz7hbMXMiK3Z6aazmr6t",
    "amount": 84549.452456418,
    "percentage": 0.13459943838973176,
    "double_amount_for_100_apy": 169098.904912836,
    "sol_equivalent_for_100_apy": 0.22965339314675198,
    "daily_sol_for_100_apy": 0.000629187378484252
  },
  {
    "owner": "52JYwt7CpEuMvKbbUDHHE1UmDrpES9cnNGjSAi3d7sLk",
    "amount": 87628.317635026,
    "percentage": 0.13950087195172856,
    "double_amount_for_100_apy": 175256.635270052,
    "sol_equivalent_for_100_apy": 0.238016212949437,
    "daily_sol_for_100_apy": 0.0006520992135601014
  },
  {
    "owner": "EbBaXL4hZzfMq8UyAbhUrKqreCWuhMkDVcp8PFqJb7x9",
    "amount": 63950.644019962,
    "percentage": 0.10180693688330497,
    "double_amount_for_100_apy": 127901.288039924,
    "sol_equivalent_for_100_apy": 0.17370286816079186,
    "daily_sol_for_100_apy": 0.0004758982689336763
  },
  {
    "owner": "2hiwSGtEfvwzHfgXE3XpzGPNCN2iwsfJoHunoCkcNwhj",
    "amount": 122594.745504408,
    "percentage": 0.1951660645340209,
    "double_amount_for_100_apy": 245189.491008816,
    "sol_equivalent_for_100_apy": 0.3329920947928347,
    "daily_sol_for_100_apy": 0.0009123071090214649
  },
  {
    "owner": "AeJdTTxEVQPfyMuQmt5gbYbp26K6NPXG4Ha4Ybtop31L",
    "amount": 85686.655329614,
    "percentage": 0.13640982111392824,
    "double_amount_for_100_apy": 171373.310659228,
    "sol_equivalent_for_100_apy": 0.2327422658826259,
    "daily_sol_for_100_apy": 0.0006376500435140435
  },
  {
    "owner": "H6bughJVtUV3emRGxpzScRGnqGJY15BFfvpfonPpQ3SE",
    "amount": 147839.114403241,
    "percentage": 0.23535411753220692,
    "double_amount_for_100_apy": 295678.228806482,
    "sol_equivalent_for_100_apy": 0.4015609004684681,
    "daily_sol_for_100_apy": 0.0011001668505985426
  },
  {
    "owner": "HcoXimDTvHHwMCVYL9zruyjGaPsHsxHtbK2weFi1iaUQ",
    "amount": 443103.114565642,
    "percentage": 0.7054029167133786,
    "double_amount_for_100_apy": 886206.229131284,
    "sol_equivalent_for_100_apy": 1.2035575727275953,
    "daily_sol_for_100_apy": 0.003297418007472864
  },
  {
    "owner": "C3gfPwiTcLPe9rSnPFJA4i8RYRUg1c3y1wwe9itCV9uD",
    "amount": 85382.59003643,
    "percentage": 0.13592576099872558,
    "double_amount_for_100_apy": 170765.18007286,
    "sol_equivalent_for_100_apy": 0.23191636312052508,
    "daily_sol_for_100_apy": 0.0006353872962206167
  },
  {
    "owner": "7hs4RpVKnaw4BnR69izpBuMgMzyNzVePGN3rMNRgHTRX",
    "amount": 32804.591886205,
    "percentage": 0.052223633816712835,
    "double_amount_for_100_apy": 65609.18377241,
    "sol_equivalent_for_100_apy": 0.08910389858934584,
    "daily_sol_for_100_apy": 0.00024412027010779682
  },
  {
    "owner": "BBTD1oGYpMj9eyusWAFMfzWZgEq9ujLPNvhP2xEMJm31",
    "amount": 85185.816883706,
    "percentage": 0.13561250579626902,
    "double_amount_for_100_apy": 170371.633767412,
    "sol_equivalent_for_100_apy": 0.23138188748655752,
    "daily_sol_for_100_apy": 0.0006339229794152261
  },
  {
    "owner": "D4j6HS8x8zXEwGpsuMcHaQEmKNbK98h4fy2ZGxzCu2ZJ",
    "amount": 357444.847628522,
    "percentage": 0.5690382888156742,
    "double_amount_for_100_apy": 714889.695257044,
    "sol_equivalent_for_100_apy": 0.9708924154538701,
    "daily_sol_for_100_apy": 0.002659979220421562
  },
  {
    "owner": "CCK7AxcYxJe65Y1yLcsVYUmaJA38HXWeEDfyWTz7KbS3",
    "amount": 33235.341498095,
    "percentage": 0.05290937043785622,
    "double_amount_for_100_apy": 66470.68299619,
    "sol_equivalent_for_100_apy": 0.09027390155321098,
    "daily_sol_for_100_apy": 0.0002473257576800301
  },
  {
    "owner": "5twSDrFqGfQ3RMEX1kXVweafMDiqQDhdDkhCyCrwXucp",
    "amount": 83637.29935928,
    "percentage": 0.13314732615206218,
    "double_amount_for_100_apy": 167274.59871856,
    "sol_equivalent_for_100_apy": 0.22717580106612864,
    "daily_sol_for_100_apy": 0.0006223994549756949
  },
  {
    "owner": "3JeCh7isYjwsdRP5Vy4Cmn1fpHzuU2gcRoRPzWc7S4mc",
    "amount": 59359.297571959,
    "percentage": 0.09449769199289668,
    "double_amount_for_100_apy": 118718.595143918,
    "sol_equivalent_for_100_apy": 0.16123184368621366,
    "daily_sol_for_100_apy": 0.0004417310785923662
  },
  {
    "owner": "JD8vN6oQ81qwqf3n4DHKEngMi5yXCas8En3E1HUE7Vj5",
    "amount": 84383.452173446,
    "percentage": 0.134335172398511,
    "double_amount_for_100_apy": 168766.904346892,
    "sol_equivalent_for_100_apy": 0.22920250284361854,
    "daily_sol_for_100_apy": 0.0006279520625852563
  },
  {
    "owner": "CqESndD3BioCn7EfJVTh2yi9NMAzoNz2dVDDr7eDEA59",
    "amount": 85976.967249788,
    "percentage": 0.13687198639445924,
    "double_amount_for_100_apy": 171953.934499576,
    "sol_equivalent_for_100_apy": 0.23353081170524104,
    "daily_sol_for_100_apy": 0.0006398104430280576
  },
  {
    "owner": "FTbZTMKAjmGQhmYoHuEyr7eNPS3pveX7pjdiiH4ayMeM",
    "amount": 2198767.827156928,
    "percentage": 3.5003528241331385,
    "double_amount_for_100_apy": 4397535.654313856,
    "sol_equivalent_for_100_apy": 5.972297603095469,
    "daily_sol_for_100_apy": 0.016362459186562928
  },
  {
    "owner": "6ecsPGq1GCM7wLUeBkzXuscfVoEwxuiTPopaRS5Eokki",
    "amount": 84547.417463276,
    "percentage": 0.13459619875983372,
    "double_amount_for_100_apy": 169094.834926552,
    "sol_equivalent_for_100_apy": 0.22964786569427872,
    "daily_sol_for_100_apy": 0.0006291722347788458
  },
  {
    "owner": "2Rad1hnCrxuafQP3hHCGJ5fxBFnqXRUHYXVMGJofFow6",
    "amount": 82172.483590616,
    "percentage": 0.1308153964460924,
    "double_amount_for_100_apy": 164344.967181232,
    "sol_equivalent_for_100_apy": 0.22319706552337681,
    "daily_sol_for_100_apy": 0.0006114988096530871
  },
  {
    "owner": "9FDj7xq89xw6XHQfLC46b547RpiqtsB2LNk346KmiUtZ",
    "amount": 35586.923938311,
    "percentage": 0.05665299817977903,
    "double_amount_for_100_apy": 71173.847876622,
    "sol_equivalent_for_100_apy": 0.09666127451625056,
    "daily_sol_for_100_apy": 0.0002648254096335632
  },
  {
    "owner": "57CJEn2p9VR9DGZGvyz5wvxQBdLJbhaSrDVjPKoDQCZ9",
    "amount": 69718.242718988,
    "percentage": 0.11098872958795208,
    "double_amount_for_100_apy": 139436.485437976,
    "sol_equivalent_for_100_apy": 0.18936883136999025,
    "daily_sol_for_100_apy": 0.000518818716082165
  },
  {
    "owner": "BwY5q84jD6z4rPMRqfekwSotuHhPCsJ365HTpzojjtLs",
    "amount": 84739.177290831,
    "percentage": 0.13490147294369575,
    "double_amount_for_100_apy": 169478.354581662,
    "sol_equivalent_for_100_apy": 0.23016872412431932,
    "daily_sol_for_100_apy": 0.0006305992441762174
  },
  {
    "owner": "3EwJnK4vR8LkwEz7T53cACNSnkJmchG7nM9JVeYwEA4L",
    "amount": 84714.22593244,
    "percentage": 0.13486175135202463,
    "double_amount_for_100_apy": 169428.45186488,
    "sol_equivalent_for_100_apy": 0.23010095119437554,
    "daily_sol_for_100_apy": 0.0006304135649160973
  },
  {
    "owner": "23oKdX41ZMyZrPjVtuj1KoqJMg4y1LuiZkLBKUDr6UVP",
    "amount": 92083.071873229,
    "percentage": 0.1465926673591024,
    "double_amount_for_100_apy": 184166.143746458,
    "sol_equivalent_for_100_apy": 0.2501162253884949,
    "daily_sol_for_100_apy": 0.0006852499325712188
  },
  {
    "owner": "xbXkY8XSL465uUveXhjsb86funRwce1r5D87ihgtAec",
    "amount": 469251.027842823,
    "percentage": 0.7470293772038961,
    "double_amount_for_100_apy": 938502.055685646,
    "sol_equivalent_for_100_apy": 1.2745805874645262,
    "daily_sol_for_100_apy": 0.0034920016094918526
  },
  {
    "owner": "FYAaKu2MTKpvXgkmVKB1Cjkt7Wm7MfxuzEzohxhgfRx3",
    "amount": 84959.805803386,
    "percentage": 0.13525270495076255,
    "double_amount_for_100_apy": 169919.611606772,
    "sol_equivalent_for_100_apy": 0.2307679957347333,
    "daily_sol_for_100_apy": 0.0006322410842047488
  },
  {
    "owner": "DS2mRtamRNUxzc66FPFLPYB5cUYd57tmSkJjDCR9bBdi",
    "amount": 83367.560945722,
    "percentage": 0.1327179130935239,
    "double_amount_for_100_apy": 166735.121891444,
    "sol_equivalent_for_100_apy": 0.22644313704364372,
    "daily_sol_for_100_apy": 0.0006203921562839554
  },
  {
    "owner": "8evCNBNLc9tt5kw6N2BSrz25sQThBWFx6UqL6CDRpFwL",
    "amount": 84380.247295244,
    "percentage": 0.13433007035711908,
    "double_amount_for_100_apy": 168760.494590488,
    "sol_equivalent_for_100_apy": 0.22919379774698775,
    "daily_sol_for_100_apy": 0.0006279282130054459
  }
]